Workbook
Name Slicer_Dep_Name: #N/A
Name Slicer_Gender: #N/A
Name Slicer_Last_performance_rating: #N/A
Name Slicer_Left?: #N/A
Name Slicer_Title: #N/A
Name Timeline_DoJ: #N/A

Sheet Employee_Info
A1: Emp_Id | B1: DOB | C1: first_name | D1: last_name | E1: Gender | F1: DoJ | G1: no_of_projects | H1: Last_performance_rating | I1: Left? | J1: last_date | K1: Salary | L1: Dept_Id | M1: Title
A2: 10001 | B2: 9/2/1953 | C2: Georgi | D2: Facello | E2: M | F2: 6/26/1986 | G2: 9 | H2: C | I2: 1 | J2: 7/30/1994 | K2: 60117 | L2: d005 | M2: Senior Engineer
A3: 10003 | B3: 12/3/1959 | C3: Parto | D3: Bamford | E3: M | F3: 8/28/1986 | G3: 1 | H3: C | I3: 0 | K3: 40006 | L3: d004 | M3: Senior Engineer
A4: 10004 | B4: 5/1/1954 | C4: Chirstian | D4: Koblick | E4: M | F4: 12/1/1986 | G4: 5 | H4: A | I4: 0 | K4: 40054 | L4: d004 | M4: Senior Engineer
A5: 10006 | B5: 4/20/1953 | C5: Anneke | D5: Preusig | E5: F | F5: 6/2/1989 | G5: 10 | H5: B | I5: 0 | K5: 40000 | L5: d005 | M5: Senior Engineer
A6: 10002 | B6: 6/2/1964 | C6: Bezalel | D6: Simmel | E6: F | F6: 11/21/1985 | G6: 8 | H6: B | I6: 0 | K6: 65828 | L6: d007 | M6: Staff
A7: 10005 | B7: 1/21/1955 | C7: Kyoichi | D7: Maliniak | E7: M | F7: 9/12/1989 | G7: 6 | H7: A | I7: 0 | K7: 78228 | L7: d003 | M7: Staff
A8: 421786 | B8: 9/28/1957 | C8: Xiong | D8: Verhoeff | E8: M | F8: 11/26/1987 | G8: 2 | H8: C | I8: 0 | K8: 40000 | L8: d003 | M8: Staff
A9: 57444 | B9: 1/30/1958 | C9: Berry | D9: Babb | E9: F | F9: 3/21/1992 | G9: 9 | H9: A | I9: 0 | K9: 48973 | L9: d004 | M9: Engineer
A10: 10007 | B10: 5/23/1957 | C10: Tzvetan | D10: Zielinski | E10: F | F10: 2/10/1989 | G10: 6 | H10: B | I10: 1 | J10: 9/18/2002 | K10: 56724 | L10: d008 | M10: Staff
A11: 10008 | B11: 2/19/1958 | C11: Saniya | D11: Kalloufi | E11: M | F11: 9/15/1994 | G11: 9 | H11: C | I11: 0 | K11: 46671 | L11: d005 | M11: Assistant Engineer
A12: 282238 | B12: 10/28/1952 | C12: Abdelkader | D12: Baumann | E12: F | F12: 1/18/1991 | G12: 6 | H12: B | I12: 0 | K12: 40000 | L12: d006 | M12: Senior Engineer
A13: 10009 | B13: 4/19/1952 | C13: Sumant | D13: Peac | E13: F | F13: 2/18/1985 | G13: 8 | H13: B | I13: 0 | K13: 60929 | L13: d006 | M13: Senior Engineer
A14: 10010 | B14: 6/1/1963 | C14: Duangkaew | D14: Piveteau | E14: F | F14: 8/24/1989 | G14: 4 | H14: A | I14: 0 | K14: 72488 | L14: d004 | M14: Engineer
A15: 10010 | B15: 6/1/1963 | C15: Duangkaew | D15: Piveteau | E15: F | F15: 8/24/1989 | G15: 4 | H15: A | I15: 0 | K15: 72488 | L15: d006 | M15: Engineer
A16: 263976 | B16: 10/30/1959 | C16: Eran | D16: Cusworth | E16: M | F16: 11/14/1986 | G16: 8 | H16: B | I16: 1 | J16: 8/21/1993 | K16: 40000 | L16: d006 | M16: Senior Engineer
A17: 10011 | B17: 11/7/1953 | C17: Mary | D17: Sluis | E17: F | F17: 1/22/1990 | G17: 6 | H17: C | I17: 0 | K17: 42365 | L17: d009 | M17: Staff
A18: 273487 | B18: 4/14/1957 | C18: Christoph | D18: Parfitt | E18: M | F18: 6/28/1991 | G18: 10 | H18: A | I18: 0 | K18: 56087 | L18: d003 | M18: Staff
A19: 10012 | B19: 10/4/1960 | C19: Patricio | D19: Bridgland | E19: M | F19: 12/18/1992 | G19: 3 | H19: A | I19: 0 | K19: 40000 | L19: d005 | M19: Senior Engineer
A20: 10013 | B20: 6/7/1963 | C20: Eberhardt | D20: Terkki | E20: M | F20: 10/20/1985 | G20: 6 | H20: C | I20: 0 | K20: 40000 | L20: d003 | M20: Senior Staff
A21: 461591 | B21: 11/17/1964 | C21: Xudong | D21: Samarati | E21: M | F21: 11/13/1985 | G21: 2 | H21: A | I21: 1 | J21: 8/21/1994 | K21: 40000 | L21: d002 | M21: Senior Staff
A22: 10014 | B22: 2/12/1956 | C22: Berni | D22: Genin | E22: M | F22: 3/11/1987 | G22: 9 | H22: B | I22: 0 | K22: 46168 | L22: d005 | M22: Engineer
A23: 10015 | B23: 8/19/1959 | C23: Guoxiang | D23: Nooteboom | E23: M | F23: 7/2/1987 | G23: 4 | H23: B | I23: 0 | K23: 40000 | L23: d008 | M23: Senior Staff
A24: 10016 | B24: 5/2/1961 | C24: Kazuhito | D24: Cappelletti | E24: M | F24: 1/27/1995 | G24: 5 | H24: C | I24: 0 | K24: 70889 | L24: d007 | M24: Staff
A25: 10017 | B25: 7/6/1958 | C25: Cristinel | D25: Bouloucos | E25: F | F25: 8/3/1993 | G25: 10 | H25: A | I25: 0 | K25: 71380 | L25: d001 | M25: Staff
A26: 219881 | B26: 4/24/1956 | C26: Kwangyoen | D26: Speek | E26: F | F26: 2/14/1993 | G26: 6 | H26: B | I26: 0 | K26: 40000 | L26: d009 | M26: Senior Staff
A27: 10018 | B27: 6/19/1954 | C27: Kazuhide | D27: Peha | E27: F | F27: 4/3/1987 | G27: 4 | H27: B | I27: 0 | K27: 55881 | L27: d004 | M27: Senior Engineer
A28: 10018 | B28: 6/19/1954 | C28: Kazuhide | D28: Peha | E28: F | F28: 4/3/1987 | G28: 4 | H28: B | I28: 0 | K28: 55881 | L28: d005 | M28: Senior Engineer
A29: 29920 | B29: 12/31/1961 | C29: Shuichi | D29: Tyugu | E29: F | F29: 1/17/1995 | G29: 1 | H29: PIP | I29: 0 | K29: 40000 | L29: d004 | M29: Engineer
A30: 10019 | B30: 1/23/1953 | C30: Lillian | D30: Haddadi | E30: M | F30: 4/30/1999 | G30: 4 | H30: B | I30: 0 | K30: 44276 | L30: d008 | M30: Staff
A31: 10020 | B31: 12/24/1952 | C31: Mayuko | D31: Warwick | E31: M | F31: 1/26/1991 | G31: 7 | H31: B | I31: 0 | K31: 40000 | L31: d004 | M31: Engineer
A32: 208153 | B32: 10/25/1961 | C32: Abdulah | D32: Lunn | E32: M | F32: 4/8/1989 | G32: 8 | H32: C | I32: 1 | J32: 8/2/2000 | K32: 50183 | L32: d005 | M32: Senior Engineer
A33: 10021 | B33: 2/20/1960 | C33: Ramzi | D33: Erde | E33: M | F33: 2/10/1988 | G33: 1 | H33: B | I33: 0 | K33: 55025 | L33: d005 | M33: Technique Leader
A34: 10022 | B34: 7/8/1952 | C34: Shahaf | D34: Famili | E34: M | F34: 8/22/1995 | G34: 9 | H34: B | I34: 1 | J34: 11/4/2005 | K34: 40000 | L34: d005 | M34: Engineer
A35: 13616 | B35: 8/30/1961 | C35: Perry | D35: Lorho | E35: F | F35: 8/3/1991 | G35: 7 | H35: C | I35: 0 | K35: 40000 | L35: d005 | M35: Senior Engineer
A36: 13616 | B36: 8/30/1961 | C36: Perry | D36: Lorho | E36: F | F36: 8/3/1991 | G36: 7 | H36: C | I36: 0 | K36: 40000 | L36: d008 | M36: Senior Engineer
A37: 10023 | B37: 9/29/1953 | C37: Bojan | D37: Montemayor | E37: F | F37: 12/17/1989 | G37: 8 | H37: A | I37: 0 | K37: 47883 | L37: d005 | M37: Engineer
A38: 10024 | B38: 9/5/1958 | C38: Suzette | D38: Pettey | E38: F | F38: 5/19/1997 | G38: 3 | H38: A | I38: 0 | K38: 83733 | L38: d004 | M38: Assistant Engineer
A39: 246449 | B39: 3/23/1958 | C39: Subbu | D39: Bultermann | E39: F | F39: 3/25/1988 | G39: 9 | H39: C | I39: 0 | K39: 87084 | L39: d007 | M39: Staff
A40: 10025 | B40: 10/31/1958 | C40: Prasadram | D40: Heyers | E40: M | F40: 8/17/1987 | G40: 6 | H40: C | I40: 0 | K40: 40000 | L40: d005 | M40: Technique Leader
A41: 10026 | B41: 4/3/1953 | C41: Yongqiao | D41: Berztiss | E41: M | F41: 3/20/1995 | G41: 1 | H41: PIP | I41: 0 | K41: 47585 | L41: d004 | M41: Senior Engineer
A42: 21529 | B42: 5/19/1959 | C42: Bojan | D42: Zallocco | E42: M | F42: 10/14/1986 | G42: 7 | H42: C | I42: 0 | K42: 40000 | L42: d005 | M42: Engineer
A43: 10027 | B43: 7/10/1962 | C43: Divier | D43: Reistad | E43: F | F43: 7/7/1989 | G43: 10 | H43: B | I43: 0 | K43: 40000 | L43: d005 | M43: Senior Engineer
A44: 10028 | B44: 11/26/1963 | C44: Domenick | D44: Tempesti | E44: M | F44: 10/22/1991 | G44: 8 | H44: B | I44: 0 | K44: 48859 | L44: d005 | M44: Engineer
A45: 17934 | B45: 7/12/1963 | C45: Bilhanan | D45: Wuwongse | E45: M | F45: 10/6/1993 | G45: 7 | H45: C | I45: 0 | K45: 48795 | L45: d005 | M45: Technique Leader
A46: 10029 | B46: 12/13/1956 | C46: Otmar | D46: Herbst | E46: M | F46: 11/20/1985 | G46: 6 | H46: C | I46: 0 | K46: 63163 | L46: d004 | M46: Senior Engineer
... A49: 10030 | B49: 7/14/1958 | C49: Elvis | D49: Demeyer | E49: M | F49: 2/17/1994 | G49: 10 | H49: A | I49: 0 | K49: 66956 | L49: d004 | M49: Senior Engineer
A50: 10031 | B50: 1/27/1959 | C50: Karsten | D50: Joslin | E50: M | F50: 9/1/1991 | G50: 2 | H50: C | I50: 1 | J50: 8/3/1999 | K50: 40000 | L50: d005 | M50: Senior Engineer
A51: 239838 | B51: 12/11/1957 | C51: Naftali | D51: Dulli | E51: M | F51: 6/6/1993 | G51: 3 | H51: A | I51: 0 | K51: 57715 | L51: d004 | M51: Engineer
A52: 10032 | B52: 8/9/1960 | C52: Jeong | D52: Reistad | E52: F | F52: 6/20/1990 | G52: 9 | H52: C | I52: 0 | K52: 48426 | L52: d004 | M52: Senior Engineer
A53: 10033 | B53: 11/14/1956 | C53: Arif | D53: Merlo | E53: M | F53: 3/18/1987 | G53: 9 | H53: A | I53: 0 | K53: 51258 | L53: d006 | M53: Technique Leader
A54: 240129 | B54: 8/11/1952 | C54: Roddy | D54: Karnin | E54: M | F54: 5/29/1985 | G54: 10 | H54: C | I54: 0 | K54: 43548 | L54: d006 | M54: Technique Leader
A55: 10034 | B55: 12/29/1962 | C55: Bader | D55: Swan | E55: M | F55: 9/21/1988 | G55: 8 | H55: C | I55: 0 | K55: 47561 | L55: d007 | M55: Staff
A56: 10035 | B56: 2/8/1953 | C56: Alain | D56: Chappelet | E56: M | F56: 9/5/1988 | G56: 6 | H56: B | I56: 0 | K56: 41538 | L56: d004 | M56: Senior Engineer
A57: 205246 | B57: 11/25/1958 | C57: Nevio | D57: Demizu | E57: F | F57: 5/18/1986 | G57: 8 | H57: B | I57: 0 | K57: 80252 | L57: d007 | M57: Senior Staff
A58: 10036 | B58: 8/10/1959 | C58: Adamantios | D58: Portugali | E58: M | F58: 1/3/1992 | G58: 5 | H58: C | I58: 0 | K58: 42819 | L58: d003 | M58: Senior Staff
A59: 10037 | B59: 7/22/1963 | C59: Pradeep | D59: Makrucki | E59: M | F59: 12/5/1990 | G59: 4 | H59: A | I59: 0 | K59: 40000 | L59: d005 | M59: Senior Engineer
A60: 10038 | B60: 7/20/1960 | C60: Huan | D60: Lortz | E60: M | F60: 9/20/1989 | G60: 5 | H60: A | I60: 0 | K60: 40000 | L60: d009 | M60: Staff
A61: 10039 | B61: 10/1/1959 | C61: Alejandro | D61: Brender | E61: M | F61: 1/19/1988 | G61: 1 | H61: B | I61: 0 | K61: 40000 | L61: d003 | M61: Staff
A62: 424270 | B62: 1/15/1963 | C62: Kellyn | D62: Yoshizawa | E62: F | F62: 5/8/1995 | G62: 8 | H62: A | I62: 0 | K62: 60678 | L62: d002 | M62: Staff
... A76: 104639 | B76: 6/19/1960 | C76: Theron | D76: Escriba | E76: F | F76: 9/14/1999 | G76: 6 | H76: B | I76: 0 | K76: 40000 | L76: d008 | M76: Senior Engineer
A77: 10047 | B77: 6/29/1952 | C77: Zvonko | D77: Nyanchama | E77: M | F77: 3/31/1989 | G77: 10 | H77: C | I77: 1 | J77: 4/23/1991 | K77: 54982 | L77: d004 | M77: Senior Engineer
A78: 10048 | B78: 7/11/1963 | C78: Florian | D78: Syrotiuk | E78: M | F78: 2/24/1985 | G78: 9 | H78: B | I78: 0 | K78: 40000 | L78: d005 | M78: Engineer
A79: 214555 | B79: 10/8/1960 | C79: Nechama | D79: Copas | E79: F | F79: 10/27/1987 | G79: 8 | H79: A | I79: 0 | K79: 40000 | L79: d005 | M79: Senior Engineer
A80: 10049 | B80: 4/24/1961 | C80: Basil | D80: Tramer | E80: F | F80: 5/4/1992 | G80: 3 | H80: B | I80: 0 | K80: 40000 | L80: d009 | M80: Staff
A81: 10050 | B81: 5/21/1958 | C81: Yinghua | D81: Dredge | E81: M | F81: 12/25/1990 | G81: 6 | H81: C | I81: 0 | K81: 74366 | L81: d002 | M81: Staff
A82: 10050 | B82: 5/21/1958 | C82: Yinghua | D82: Dredge | E82: M | F82: 12/25/1990 | G82: 6 | H82: C | I82: 0 | K82: 74366 | L82: d007 | M82: Staff
A83: 229010 | B83: 11/12/1961 | C83: Mark | D83: Cappelli | E83: M | F83: 5/7/1990 | G83: 9 | H83: B | I83: 0 | K83: 40000 | L83: d003 | M83: Staff
A84: 10051 | B84: 7/28/1953 | C84: Hidefumi | D84: Caine | E84: M | F84: 10/15/1992 | G84: 2 | H84: A | I84: 0 | K84: 48817 | L84: d004 | M84: Senior Engineer
A85: 35916 | B85: 8/15/1953 | C85: Wonhee | D85: Talmon | E85: F | F85: 3/20/1985 | G85: 1 | H85: A | I85: 0 | K85: 40000 | L85: d005 | M85: Senior Engineer
A86: 10052 | B86: 2/26/1961 | C86: Heping | D86: Nitsch | E86: M | F86: 5/21/1988 | G86: 5 | H86: B | I86: 0 | K86: 57212 | L86: d008 | M86: Staff
A87: 10053 | B87: 9/13/1954 | C87: Sanjiv | D87: Zschoche | E87: F | F87: 2/4/1986 | G87: 4 | H87: B | I87: 0 | K87: 67854 | L87: d007 | M87: Senior Staff
A88: 61583 | B88: 6/4/1957 | C88: Ziva | D88: Vecchi | E88: M | F88: 7/3/1986 | G88: 6 | H88: B | I88: 0 | K88: 50801 | L88: d005 | M88: Senior Engineer
A89: 10054 | B89: 4/4/1957 | C89: Mayumi | D89: Schueller | E89: M | F89: 3/13/1995 | G89: 8 | H89: A | I89: 0 | K89: 40000 | L89: d003 | M89: Staff
... A101: 10061 | B101: 10/19/1962 | C101: Tse | D101: Herber | E101: M | F101: 9/17/1985 | G101: 1 | H101: B | I101: 0 | K101: 68577 | L101: d007 | M101: Senior Staff
A102: 10062 | B102: 11/2/1961 | C102: Anoosh | D102: Peyn | E102: M | F102: 8/30/1991 | G102: 7 | H102: B | I102: 1 | J102: 2/16/1993 | K102: 55685 | L102: d005 | M102: Senior Engineer
A103: 35270 | B103: 1/2/1953 | C103: Masali | D103: Bakhtari | E103: M | F103: 2/5/1991 | G103: 4 | H103: A | I103: 0 | K103: 40338 | L103: d004 | M103: Technique Leader
A104: 10063 | B104: 8/6/1952 | C104: Gino | D104: Leonhardt | E104: F | F104: 4/8/1989 | G104: 1 | H104: A | I104: 0 | K104: 40000 | L104: d004 | M104: Senior Engineer
A105: 10064 | B105: 4/7/1959 | C105: Udi | D105: Jansch | E105: M | F105: 11/20/1985 | G105: 2 | H105: A | I105: 0 | K105: 40000 | L105: d008 | M105: Staff
A106: 105597 | B106: 8/14/1956 | C106: Christfried | D106: Kabayashi | E106: M | F106: 5/11/1987 | G106: 2 | H106: A | I106: 0 | K106: 43841 | L106: d003 | M106: Senior Staff
A107: 10065 | B107: 4/14/1963 | C107: Satosi | D107: Awdeh | E107: M | F107: 5/18/1988 | G107: 5 | H107: B | I107: 0 | K107: 40000 | L107: d005 | M107: Engineer
A108: 10066 | B108: 11/13/1952 | C108: Kwee | D108: Schusler | E108: M | F108: 2/26/1986 | G108: 1 | H108: PIP | I108: 0 | K108: 69736 | L108: d005 | M108: Senior Engineer
A109: 244689 | B109: 4/13/1956 | C109: Urs | D109: Saoudi | E109: M | F109: 9/2/1991 | G109: 7 | H109: B | I109: 0 | K109: 40000 | L109: d001 | M109: Staff
A110: 244689 | B110: 4/13/1956 | C110: Urs | D110: Saoudi | E110: M | F110: 9/2/1991 | G110: 7 | H110: B | I110: 0 | K110: 40000 | L110: d003 | M110: Staff
A111: 10067 | B111: 1/7/1953 | C111: Claudi | D111: Stavenow | E111: M | F111: 3/4/1987 | G111: 2 | H111: C | I111: 0 | K111: 44642 | L111: d006 | M111: Senior Engineer
A112: 10068 | B112: 11/26/1962 | C112: Charlene | D112: Brattka | E112: M | F112: 8/7/1987 | G112: 6 | H112: A | I112: 0 | K112: 87964 | L112: d007 | M112: Staff
A113: 48885 | B113: 8/28/1958 | C113: Phuoc | D113: Antonisse | E113: M | F113: 2/18/1993 | G113: 9 | H113: B | I113: 0 | K113: 55736 | L113: d005 | M113: Senior Engineer
A114: 10069 | B114: 9/6/1960 | C114: Margareta | D114: Bierman | E114: F | F114: 11/5/1989 | G114: 10 | H114: A | I114: 0 | K114: 67932 | L114: d004 | M114: Technique Leader
... A116: 10070 | B116: 8/20/1955 | C116: Reuven | D116: Garigliano | E116: M | F116: 10/14/1985 | G116: 7 | H116: A | I116: 0 | K116: 55999 | L116: d008 | M116: Technique Leader
A117: 244492 | B117: 5/22/1958 | C117: Shaunak | D117: Pettit | E117: M | F117: 7/19/1994 | G117: 3 | H117: C | I117: 1 | J117: 11/14/2000 | K117: 63685 | L117: d005 | M117: Senior Engineer
A118: 10071 | B118: 1/21/1958 | C118: Hisao | D118: Lipner | E118: M | F118: 10/1/1987 | G118: 4 | H118: B | I118: 0 | K118: 40000 | L118: d003 | M118: Staff
A119: 215615 | B119: 2/13/1957 | C119: Bader | D119: Chinal | E119: F | F119: 1/8/1990 | G119: 10 | H119: C | I119: 0 | K119: 40000 | L119: d004 | M119: Engineer
A120: 215615 | B120: 2/13/1957 | C120: Bader | D120: Chinal | E120: F | F120: 1/8/1990 | G120: 10 | H120: C | I120: 0 | K120: 40000 | L120: d006 | M120: Engineer
A121: 10072 | B121: 5/15/1952 | C121: Hironoby | D121: Sidou | E121: F | F121: 7/21/1988 | G121: 8 | H121: B | I121: 0 | K121: 40000 | L121: d005 | M121: Senior Engineer
A122: 10073 | B122: 2/23/1954 | C122: Shir | D122: McClurg | E122: M | F122: 12/1/1991 | G122: 5 | H122: C | I122: 0 | K122: 56473 | L122: d006 | M122: Engineer
A123: 95280 | B123: 2/14/1960 | C123: Owen | D123: Hiraishi | E123: F | F123: 8/7/1985 | G123: 10 | H123: S | I123: 0 | K123: 40000 | L123: d004 | M123: Senior Engineer
A124: 10074 | B124: 8/28/1955 | C124: Mokhtar | D124: Bernatsky | E124: F | F124: 8/13/1990 | G124: 8 | H124: PIP | I124: 1 | J124: 5/22/1995 | K124: 61714 | L124: d005 | M124: Technique Leader
A125: 10075 | B125: 3/9/1960 | C125: Gao | D125: Dolinsky | E125: F | F125: 3/19/1987 | G125: 4 | H125: B | I125: 0 | K125: 43815 | L125: d005 | M125: Senior Engineer
A126: 37473 | B126: 3/6/1952 | C126: Prasadram | D126: Valette | E126: M | F126: 2/16/1994 | G126: 3 | H126: PIP | I126: 0 | K126: 55963 | L126: d002 | M126: Staff
A127: 10076 | B127: 6/13/1952 | C127: Erez | D127: Ritzmann | E127: F | F127: 7/9/1985 | G127: 9 | H127: B | I127: 0 | K127: 47319 | L127: d005 | M127: Senior Engineer
...

Sheet New_employee(Cleaned)
A1: Emp_Id | B1: DOB | C1: first_name | D1: last_name | E1: Gender | F1: DoJ | G1: no_of_projects | H1: Last_performance_rating | I1: Left? | J1: last_date | K1: Salary | L1: Dept_Id | M1: Title | N1: Performance issues?
A2: 10001 | B2: 19604 | C2: Georgi | D2: Facello | E2: M | F2: 31589 | G2: 9 | H2: C | I2: 1 | J2: 34545 | K2: 60117 | L2: d005 | M2: Senior Engineer | N2: =IF(AND( Table15[[#This Row],[Salary]] >= 80000, OR(Table15[[#This Row],[Last_performance_rating]] = "C", Table15[[#This Row],[Last_performance_rating]] = "PIP")) = TRUE, 1, 0) -> 0
A3: 10003 | B3: 21887 | C3: Parto | D3: Bamford | E3: M | F3: 31652 | G3: 1 | H3: C | I3: 0 | K3: 40006 | L3: d004 | M3: Senior Engineer | N3: =IF(AND( Table15[[#This Row],[Salary]] >= 80000, OR(Table15[[#This Row],[Last_performance_rating]] = "C", Table15[[#This Row],[Last_performance_rating]] = "PIP")) = TRUE, 1, 0) -> 0
A4: 10004 | B4: 19845 | C4: Chirstian | D4: Koblick | E4: M | F4: 31747 | G4: 5 | H4: A | I4: 0 | K4: 40054 | L4: d004 | M4: Senior Engineer | N4: =IF(AND( Table15[[#This Row],[Salary]] >= 80000, OR(Table15[[#This Row],[Last_performance_rating]] = "C", Table15[[#This Row],[Last_performance_rating]] = "PIP")) = TRUE, 1, 0) -> 0
A5: 10006 | B5: 19469 | C5: Anneke | D5: Preusig | E5: F | F5: 32661 | G5: 10 | H5: B | I5: 0 | K5: 40000 | L5: d005 | M5: Senior Engineer | N5: =IF(AND( Table15[[#This Row],[Salary]] >= 80000, OR(Table15[[#This Row],[Last_performance_rating]] = "C", Table15[[#This Row],[Last_performance_rating]] = "PIP")) = TRUE, 1, 0) -> 0
A6: 10002 | B6: 23530 | C6: Bezalel | D6: Simmel | E6: F | F6: 31372 | G6: 8 | H6: B | I6: 0 | K6: 65828 | L6: d007 | M6: Staff | N6: =IF(AND( Table15[[#This Row],[Salary]] >= 80000, OR(Table15[[#This Row],[Last_performance_rating]] = "C", Table15[[#This Row],[Last_performance_rating]] = "PIP")) = TRUE, 1, 0) -> 0
A7: 10005 | B7: 20110 | C7: Kyoichi | D7: Maliniak | E7: M | F7: 32763 | G7: 6 | H7: A | I7: 0 | K7: 78228 | L7: d003 | M7: Staff | N7: =IF(AND( Table15[[#This Row],[Salary]] >= 80000, OR(Table15[[#This Row],[Last_performance_rating]] = "C", Table15[[#This Row],[Last_performance_rating]] = "PIP")) = TRUE, 1, 0) -> 0
A8: 421786 | B8: 21091 | C8: Xiong | D8: Verhoeff | E8: M | F8: 32107 | G8: 2 | H8: C | I8: 0 | K8: 40000 | L8: d003 | M8: Staff | N8: =IF(AND( Table15[[#This Row],[Salary]] >= 80000, OR(Table15[[#This Row],[Last_performance_rating]] = "C", Table15[[#This Row],[Last_performance_rating]] = "PIP")) = TRUE, 1, 0) -> 0
A9: 57444 | B9: 21215 | C9: Berry | D9: Babb | E9: F | F9: 33684 | G9: 9 | H9: A | I9: 0 | K9: 48973 | L9: d004 | M9: Engineer | N9: =IF(AND( Table15[[#This Row],[Salary]] >= 80000, OR(Table15[[#This Row],[Last_performance_rating]] = "C", Table15[[#This Row],[Last_performance_rating]] = "PIP")) = TRUE, 1, 0) -> 0
A10: 10007 | B10: 20963 | C10: Tzvetan | D10: Zielinski | E10: F | F10: 32549 | G10: 6 | H10: B | I10: 1 | J10: 37517 | K10: 56724 | L10: d008 | M10: Staff | N10: =IF(AND( Table15[[#This Row],[Salary]] >= 80000, OR(Table15[[#This Row],[Last_performance_rating]] = "C", Table15[[#This Row],[Last_performance_rating]] = "PIP")) = TRUE, 1, 0) -> 0
A11: 10008 | B11: 21235 | C11: Saniya | D11: Kalloufi | E11: M | F11: 34592 | G11: 9 | H11: C | I11: 0 | K11: 46671 | L11: d005 | M11: Assistant Engineer | N11: =IF(AND( Table15[[#This Row],[Salary]] >= 80000, OR(Table15[[#This Row],[Last_performance_rating]] = "C", Table15[[#This Row],[Last_performance_rating]] = "PIP")) = TRUE, 1, 0) -> 0
A12: 282238 | B12: 19295 | C12: Abdelkader | D12: Baumann | E12: F | F12: 33256 | G12: 6 | H12: B | I12: 0 | K12: 40000 | L12: d006 | M12: Senior Engineer | N12: =IF(AND( Table15[[#This Row],[Salary]] >= 80000, OR(Table15[[#This Row],[Last_performance_rating]] = "C", Table15[[#This Row],[Last_performance_rating]] = "PIP")) = TRUE, 1, 0) -> 0
A13: 10009 | B13: 19103 | C13: Sumant | D13: Peac | E13: F | F13: 31096 | G13: 8 | H13: B | I13: 0 | K13: 60929 | L13: d006 | M13: Senior Engineer | N13: =IF(AND( Table15[[#This Row],[Salary]] >= 80000, OR(Table15[[#This Row],[Last_performance_rating]] = "C", Table15[[#This Row],[Last_performance_rating]] = "PIP")) = TRUE, 1, 0) -> 0
A14: 10010 | B14: 23163 | C14: Duangkaew | D14: Piveteau | E14: F | F14: 32744 | G14: 4 | H14: A | I14: 0 | K14: 72488 | L14: d004 | M14: Engineer | N14: =IF(AND( Table15[[#This Row],[Salary]] >= 80000, OR(Table15[[#This Row],[Last_performance_rating]] = "C", Table15[[#This Row],[Last_performance_rating]] = "PIP")) = TRUE, 1, 0) -> 0
A15: 10010 | B15: 23163 | C15: Duangkaew | D15: Piveteau | E15: F | F15: 32744 | G15: 4 | H15: A | I15: 0 | K15: 72488 | L15: d006 | M15: Engineer | N15: =IF(AND( Table15[[#This Row],[Salary]] >= 80000, OR(Table15[[#This Row],[Last_performance_rating]] = "C", Table15[[#This Row],[Last_performance_rating]] = "PIP")) = TRUE, 1, 0) -> 0
A16: 263976 | B16: 21853 | C16: Eran | D16: Cusworth | E16: M | F16: 31730 | G16: 8 | H16: B | I16: 1 | J16: 34202 | K16: 40000 | L16: d006 | M16: Senior Engineer | N16: =IF(AND( Table15[[#This Row],[Salary]] >= 80000, OR(Table15[[#This Row],[Last_performance_rating]] = "C", Table15[[#This Row],[Last_performance_rating]] = "PIP")) = TRUE, 1, 0) -> 0
A17: 10011 | B17: 19670 | C17: Mary | D17: Sluis | E17: F | F17: 32895 | G17: 6 | H17: C | I17: 0 | K17: 42365 | L17: d009 | M17: Staff | N17: =IF(AND( Table15[[#This Row],[Salary]] >= 80000, OR(Table15[[#This Row],[Last_performance_rating]] = "C", Table15[[#This Row],[Last_performance_rating]] = "PIP")) = TRUE, 1, 0) -> 0
A18: 273487 | B18: 20924 | C18: Christoph | D18: Parfitt | E18: M | F18: 33417 | G18: 10 | H18: A | I18: 0 | K18: 56087 | L18: d003 | M18: Staff | N18: =IF(AND( Table15[[#This Row],[Salary]] >= 80000, OR(Table15[[#This Row],[Last_performance_rating]] = "C", Table15[[#This Row],[Last_performance_rating]] = "PIP")) = TRUE, 1, 0) -> 0
A19: 10012 | B19: 22193 | C19: Patricio | D19: Bridgland | E19: M | F19: 33956 | G19: 3 | H19: A | I19: 0 | K19: 40000 | L19: d005 | M19: Senior Engineer | N19: =IF(AND( Table15[[#This Row],[Salary]] >= 80000, OR(Table15[[#This Row],[Last_performance_rating]] = "C", Table15[[#This Row],[Last_performance_rating]] = "PIP")) = TRUE, 1, 0) -> 0
A20: 10013 | B20: 23169 | C20: Eberhardt | D20: Terkki | E20: M | F20: 31340 | G20: 6 | H20: C | I20: 0 | K20: 40000 | L20: d003 | M20: Senior Staff | N20: =IF(AND( Table15[[#This Row],[Salary]] >= 80000, OR(Table15[[#This Row],[Last_performance_rating]] = "C", Table15[[#This Row],[Last_performance_rating]] = "PIP")) = TRUE, 1, 0) -> 0
A21: 461591 | B21: 23698 | C21: Xudong | D21: Samarati | E21: M | F21: 31364 | G21: 2 | H21: A | I21: 1 | J21: 34567 | K21: 40000 | L21: d002 | M21: Senior Staff | N21: =IF(AND( Table15[[#This Row],[Salary]] >= 80000, OR(Table15[[#This Row],[Last_performance_rating]] = "C", Table15[[#This Row],[Last_performance_rating]] = "PIP")) = TRUE, 1, 0) -> 0
A22: 10014 | B22: 20497 | C22: Berni | D22: Genin | E22: M | F22: 31847 | G22: 9 | H22: B | I22: 0 | K22: 46168 | L22: d005 | M22: Engineer | N22: =IF(AND( Table15[[#This Row],[Salary]] >= 80000, OR(Table15[[#This Row],[Last_performance_rating]] = "C", Table15[[#This Row],[Last_performance_rating]] = "PIP")) = TRUE, 1, 0) -> 0
A23: 10015 | B23: 21781 | C23: Guoxiang | D23: Nooteboom | E23: M | F23: 31960 | G23: 4 | H23: B | I23: 0 | K23: 40000 | L23: d008 | M23: Senior Staff | N23: =IF(AND( Table15[[#This Row],[Salary]] >= 80000, OR(Table15[[#This Row],[Last_performance_rating]] = "C", Table15[[#This Row],[Last_performance_rating]] = "PIP")) = TRUE, 1, 0) -> 0
A24: 10016 | B24: 22403 | C24: Kazuhito | D24: Cappelletti | E24: M | F24: 34726 | G24: 5 | H24: C | I24: 0 | K24: 70889 | L24: d007 | M24: Staff | N24: =IF(AND( Table15[[#This Row],[Salary]] >= 80000, OR(Table15[[#This Row],[Last_performance_rating]] = "C", Table15[[#This Row],[Last_performance_rating]] = "PIP")) = TRUE, 1, 0) -> 0
A25: 10017 | B25: 21372 | C25: Cristinel | D25: Bouloucos | E25: F | F25: 34184 | G25: 10 | H25: A | I25: 0 | K25: 71380 | L25: d001 | M25: Staff | N25: =IF(AND( Table15[[#This Row],[Salary]] >= 80000, OR(Table15[[#This Row],[Last_performance_rating]] = "C", Table15[[#This Row],[Last_performance_rating]] = "PIP")) = TRUE, 1, 0) -> 0
A26: 219881 | B26: 20569 | C26: Kwangyoen | D26: Speek | E26: F | F26: 34014 | G26: 6 | H26: B | I26: 0 | K26: 40000 | L26: d009 | M26: Senior Staff | N26: =IF(AND( Table15[[#This Row],[Salary]] >= 80000, OR(Table15[[#This Row],[Last_performance_rating]] = "C", Table15[[#This Row],[Last_performance_rating]] = "PIP")) = TRUE, 1, 0) -> 0
A27: 10018 | B27: 19894 | C27: Kazuhide | D27: Peha | E27: F | F27: 31870 | G27: 4 | H27: B | I27: 0 | K27: 55881 | L27: d004 | M27: Senior Engineer | N27: =IF(AND( Table15[[#This Row],[Salary]] >= 80000, OR(Table15[[#This Row],[Last_performance_rating]] = "C", Table15[[#This Row],[Last_performance_rating]] = "PIP")) = TRUE, 1, 0) -> 0
A28: 10018 | B28: 19894 | C28: Kazuhide | D28: Peha | E28: F | F28: 31870 | G28: 4 | H28: B | I28: 0 | K28: 55881 | L28: d005 | M28: Senior Engineer | N28: =IF(AND( Table15[[#This Row],[Salary]] >= 80000, OR(Table15[[#This Row],[Last_performance_rating]] = "C", Table15[[#This Row],[Last_performance_rating]] = "PIP")) = TRUE, 1, 0) -> 0
A29: 29920 | B29: 22646 | C29: Shuichi | D29: Tyugu | E29: F | F29: 34716 | G29: 1 | H29: PIP | I29: 0 | K29: 40000 | L29: d004 | M29: Engineer | N29: =IF(AND( Table15[[#This Row],[Salary]] >= 80000, OR(Table15[[#This Row],[Last_performance_rating]] = "C", Table15[[#This Row],[Last_performance_rating]] = "PIP")) = TRUE, 1, 0) -> 0
A30: 10019 | B30: 19382 | C30: Lillian | D30: Haddadi | E30: M | F30: 36280 | G30: 4 | H30: B | I30: 0 | K30: 44276 | L30: d008 | M30: Staff | N30: =IF(AND( Table15[[#This Row],[Salary]] >= 80000, OR(Table15[[#This Row],[Last_performance_rating]] = "C", Table15[[#This Row],[Last_performance_rating]] = "PIP")) = TRUE, 1, 0) -> 0
A31: 10020 | B31: 19352 | C31: Mayuko | D31: Warwick | E31: M | F31: 33264 | G31: 7 | H31: B | I31: 0 | K31: 40000 | L31: d004 | M31: Engineer | N31: =IF(AND( Table15[[#This Row],[Salary]] >= 80000, OR(Table15[[#This Row],[Last_performance_rating]] = "C", Table15[[#This Row],[Last_performance_rating]] = "PIP")) = TRUE, 1, 0) -> 0
A32: 208153 | B32: 22579 | C32: Abdulah | D32: Lunn | E32: M | F32: 32606 | G32: 8 | H32: C | I32: 1 | J32: 36740 | K32: 50183 | L32: d005 | M32: Senior Engineer | N32: =IF(AND( Table15[[#This Row],[Salary]] >= 80000, OR(Table15[[#This Row],[Last_performance_rating]] = "C", Table15[[#This Row],[Last_performance_rating]] = "PIP")) = TRUE, 1, 0) -> 0
A33: 10021 | B33: 21966 | C33: Ramzi | D33: Erde | E33: M | F33: 32183 | G33: 1 | H33: B | I33: 0 | K33: 55025 | L33: d005 | M33: Technique Leader | N33: =IF(AND( Table15[[#This Row],[Salary]] >= 80000, OR(Table15[[#This Row],[Last_performance_rating]] = "C", Table15[[#This Row],[Last_performance_rating]] = "PIP")) = TRUE, 1, 0) -> 0
A34: 10022 | B34: 19183 | C34: Shahaf | D34: Famili | E34: M | F34: 34933 | G34: 9 | H34: B | I34: 1 | J34: 38660 | K34: 40000 | L34: d005 | M34: Engineer | N34: =IF(AND( Table15[[#This Row],[Salary]] >= 80000, OR(Table15[[#This Row],[Last_performance_rating]] = "C", Table15[[#This Row],[Last_performance_rating]] = "PIP")) = TRUE, 1, 0) -> 0
A35: 13616 | B35: 22523 | C35: Perry | D35: Lorho | E35: F | F35: 33453 | G35: 7 | H35: C | I35: 0 | K35: 40000 | L35: d005 | M35: Senior Engineer | N35: =IF(AND( Table15[[#This Row],[Salary]] >= 80000, OR(Table15[[#This Row],[Last_performance_rating]] = "C", Table15[[#This Row],[Last_performance_rating]] = "PIP")) = TRUE, 1, 0) -> 0
A36: 13616 | B36: 22523 | C36: Perry | D36: Lorho | E36: F | F36: 33453 | G36: 7 | H36: C | I36: 0 | K36: 40000 | L36: d008 | M36: Senior Engineer | N36: =IF(AND( Table15[[#This Row],[Salary]] >= 80000, OR(Table15[[#This Row],[Last_performance_rating]] = "C", Table15[[#This Row],[Last_performance_rating]] = "PIP")) = TRUE, 1, 0) -> 0
A37: 10023 | B37: 19631 | C37: Bojan | D37: Montemayor | E37: F | F37: 32859 | G37: 8 | H37: A | I37: 0 | K37: 47883 | L37: d005 | M37: Engineer | N37: =IF(AND( Table15[[#This Row],[Salary]] >= 80000, OR(Table15[[#This Row],[Last_performance_rating]] = "C", Table15[[#This Row],[Last_performance_rating]] = "PIP")) = TRUE, 1, 0) -> 0
A38: 10024 | B38: 21433 | C38: Suzette | D38: Pettey | E38: F | F38: 35569 | G38: 3 | H38: A | I38: 0 | K38: 83733 | L38: d004 | M38: Assistant Engineer | N38: =IF(AND( Table15[[#This Row],[Salary]] >= 80000, OR(Table15[[#This Row],[Last_performance_rating]] = "C", Table15[[#This Row],[Last_performance_rating]] = "PIP")) = TRUE, 1, 0) -> 0
A39: 246449 | B39: 21267 | C39: Subbu | D39: Bultermann | E39: F | F39: 32227 | G39: 9 | H39: C | I39: 0 | K39: 87084 | L39: d007 | M39: Staff | N39: =IF(AND( Table15[[#This Row],[Salary]] >= 80000, OR(Table15[[#This Row],[Last_performance_rating]] = "C", Table15[[#This Row],[Last_performance_rating]] = "PIP")) = TRUE, 1, 0) -> 1
A40: 10025 | B40: 21489 | C40: Prasadram | D40: Heyers | E40: M | F40: 32006 | G40: 6 | H40: C | I40: 0 | K40: 40000 | L40: d005 | M40: Technique Leader | N40: =IF(AND( Table15[[#This Row],[Salary]] >= 80000, OR(Table15[[#This Row],[Last_performance_rating]] = "C", Table15[[#This Row],[Last_performance_rating]] = "PIP")) = TRUE, 1, 0) -> 0
A41: 10026 | B41: 19452 | C41: Yongqiao | D41: Berztiss | E41: M | F41: 34778 | G41: 1 | H41: PIP | I41: 0 | K41: 47585 | L41: d004 | M41: Senior Engineer | N41: =IF(AND( Table15[[#This Row],[Salary]] >= 80000, OR(Table15[[#This Row],[Last_performance_rating]] = "C", Table15[[#This Row],[Last_performance_rating]] = "PIP")) = TRUE, 1, 0) -> 0
A42: 21529 | B42: 21689 | C42: Bojan | D42: Zallocco | E42: M | F42: 31699 | G42: 7 | H42: C | I42: 0 | K42: 40000 | L42: d005 | M42: Engineer | N42: =IF(AND( Table15[[#This Row],[Salary]] >= 80000, OR(Table15[[#This Row],[Last_performance_rating]] = "C", Table15[[#This Row],[Last_performance_rating]] = "PIP")) = TRUE, 1, 0) -> 0
A43: 10027 | B43: 22837 | C43: Divier | D43: Reistad | E43: F | F43: 32696 | G43: 10 | H43: B | I43: 0 | K43: 40000 | L43: d005 | M43: Senior Engineer | N43: =IF(AND( Table15[[#This Row],[Salary]] >= 80000, OR(Table15[[#This Row],[Last_performance_rating]] = "C", Table15[[#This Row],[Last_performance_rating]] = "PIP")) = TRUE, 1, 0) -> 0
A44: 10028 | B44: 23341 | C44: Domenick | D44: Tempesti | E44: M | F44: 33533 | G44: 8 | H44: B | I44: 0 | K44: 48859 | L44: d005 | M44: Engineer | N44: =IF(AND( Table15[[#This Row],[Salary]] >= 80000, OR(Table15[[#This Row],[Last_performance_rating]] = "C", Table15[[#This Row],[Last_performance_rating]] = "PIP")) = TRUE, 1, 0) -> 0
A45: 17934 | B45: 23204 | C45: Bilhanan | D45: Wuwongse | E45: M | F45: 34248 | G45: 7 | H45: C | I45: 0 | K45: 48795 | L45: d005 | M45: Technique Leader | N45: =IF(AND( Table15[[#This Row],[Salary]] >= 80000, OR(Table15[[#This Row],[Last_performance_rating]] = "C", Table15[[#This Row],[Last_performance_rating]] = "PIP")) = TRUE, 1, 0) -> 0
A46: 10029 | B46: 20802 | C46: Otmar | D46: Herbst | E46: M | F46: 31371 | G46: 6 | H46: C | I46: 0 | K46: 63163 | L46: d004 | M46: Senior Engineer | N46: =IF(AND( Table15[[#This Row],[Salary]] >= 80000, OR(Table15[[#This Row],[Last_performance_rating]] = "C", Table15[[#This Row],[Last_performance_rating]] = "PIP")) = TRUE, 1, 0) -> 0
... A49: 10030 | B49: 21380 | C49: Elvis | D49: Demeyer | E49: M | F49: 34382 | G49: 10 | H49: A | I49: 0 | K49: 66956 | L49: d004 | M49: Senior Engineer | N49: =IF(AND( Table15[[#This Row],[Salary]] >= 80000, OR(Table15[[#This Row],[Last_performance_rating]] = "C", Table15[[#This Row],[Last_performance_rating]] = "PIP")) = TRUE, 1, 0) -> 0
A50: 10031 | B50: 21577 | C50: Karsten | D50: Joslin | E50: M | F50: 33482 | G50: 2 | H50: C | I50: 1 | J50: 36375 | K50: 40000 | L50: d005 | M50: Senior Engineer | N50: =IF(AND( Table15[[#This Row],[Salary]] >= 80000, OR(Table15[[#This Row],[Last_performance_rating]] = "C", Table15[[#This Row],[Last_performance_rating]] = "PIP")) = TRUE, 1, 0) -> 0
A51: 239838 | B51: 21165 | C51: Naftali | D51: Dulli | E51: M | F51: 34126 | G51: 3 | H51: A | I51: 0 | K51: 57715 | L51: d004 | M51: Engineer | N51: =IF(AND( Table15[[#This Row],[Salary]] >= 80000, OR(Table15[[#This Row],[Last_performance_rating]] = "C", Table15[[#This Row],[Last_performance_rating]] = "PIP")) = TRUE, 1, 0) -> 0
A52: 10032 | B52: 22137 | C52: Jeong | D52: Reistad | E52: F | F52: 33044 | G52: 9 | H52: C | I52: 0 | K52: 48426 | L52: d004 | M52: Senior Engineer | N52: =IF(AND( Table15[[#This Row],[Salary]] >= 80000, OR(Table15[[#This Row],[Last_performance_rating]] = "C", Table15[[#This Row],[Last_performance_rating]] = "PIP")) = TRUE, 1, 0) -> 0
A53: 10033 | B53: 20773 | C53: Arif | D53: Merlo | E53: M | F53: 31854 | G53: 9 | H53: A | I53: 0 | K53: 51258 | L53: d006 | M53: Technique Leader | N53: =IF(AND( Table15[[#This Row],[Salary]] >= 80000, OR(Table15[[#This Row],[Last_performance_rating]] = "C", Table15[[#This Row],[Last_performance_rating]] = "PIP")) = TRUE, 1, 0) -> 0
A54: 240129 | B54: 19217 | C54: Roddy | D54: Karnin | E54: M | F54: 31196 | G54: 10 | H54: C | I54: 0 | K54: 43548 | L54: d006 | M54: Technique Leader | N54: =IF(AND( Table15[[#This Row],[Salary]] >= 80000, OR(Table15[[#This Row],[Last_performance_rating]] = "C", Table15[[#This Row],[Last_performance_rating]] = "PIP")) = TRUE, 1, 0) -> 0
A55: 10034 | B55: 23009 | C55: Bader | D55: Swan | E55: M | F55: 32407 | G55: 8 | H55: C | I55: 0 | K55: 47561 | L55: d007 | M55: Staff | N55: =IF(AND( Table15[[#This Row],[Salary]] >= 80000, OR(Table15[[#This Row],[Last_performance_rating]] = "C", Table15[[#This Row],[Last_performance_rating]] = "PIP")) = TRUE, 1, 0) -> 0
A56: 10035 | B56: 19398 | C56: Alain | D56: Chappelet | E56: M | F56: 32391 | G56: 6 | H56: B | I56: 0 | K56: 41538 | L56: d004 | M56: Senior Engineer | N56: =IF(AND( Table15[[#This Row],[Salary]] >= 80000, OR(Table15[[#This Row],[Last_performance_rating]] = "C", Table15[[#This Row],[Last_performance_rating]] = "PIP")) = TRUE, 1, 0) -> 0
A57: 205246 | B57: 21514 | C57: Nevio | D57: Demizu | E57: F | F57: 31550 | G57: 8 | H57: B | I57: 0 | K57: 80252 | L57: d007 | M57: Senior Staff | N57: =IF(AND( Table15[[#This Row],[Salary]] >= 80000, OR(Table15[[#This Row],[Last_performance_rating]] = "C", Table15[[#This Row],[Last_performance_rating]] = "PIP")) = TRUE, 1, 0) -> 0
A58: 10036 | B58: 21772 | C58: Adamantios | D58: Portugali | E58: M | F58: 33606 | G58: 5 | H58: C | I58: 0 | K58: 42819 | L58: d003 | M58: Senior Staff | N58: =IF(AND( Table15[[#This Row],[Salary]] >= 80000, OR(Table15[[#This Row],[Last_performance_rating]] = "C", Table15[[#This Row],[Last_performance_rating]] = "PIP")) = TRUE, 1, 0) -> 0
A59: 10037 | B59: 23214 | C59: Pradeep | D59: Makrucki | E59: M | F59: 33212 | G59: 4 | H59: A | I59: 0 | K59: 40000 | L59: d005 | M59: Senior Engineer | N59: =IF(AND( Table15[[#This Row],[Salary]] >= 80000, OR(Table15[[#This Row],[Last_performance_rating]] = "C", Table15[[#This Row],[Last_performance_rating]] = "PIP")) = TRUE, 1, 0) -> 0
A60: 10038 | B60: 22117 | C60: Huan | D60: Lortz | E60: M | F60: 32771 | G60: 5 | H60: A | I60: 0 | K60: 40000 | L60: d009 | M60: Staff | N60: =IF(AND( Table15[[#This Row],[Salary]] >= 80000, OR(Table15[[#This Row],[Last_performance_rating]] = "C", Table15[[#This Row],[Last_performance_rating]] = "PIP")) = TRUE, 1, 0) -> 0
A61: 10039 | B61: 21824 | C61: Alejandro | D61: Brender | E61: M | F61: 32161 | G61: 1 | H61: B | I61: 0 | K61: 40000 | L61: d003 | M61: Staff | N61: =IF(AND( Table15[[#This Row],[Salary]] >= 80000, OR(Table15[[#This Row],[Last_performance_rating]] = "C", Table15[[#This Row],[Last_performance_rating]] = "PIP")) = TRUE, 1, 0) -> 0
A62: 424270 | B62: 23026 | C62: Kellyn | D62: Yoshizawa | E62: F | F62: 34827 | G62: 8 | H62: A | I62: 0 | K62: 60678 | L62: d002 | M62: Staff | N62: =IF(AND( Table15[[#This Row],[Salary]] >= 80000, OR(Table15[[#This Row],[Last_performance_rating]] = "C", Table15[[#This Row],[Last_performance_rating]] = "PIP")) = TRUE, 1, 0) -> 0
... A76: 104639 | B76: 22086 | C76: Theron | D76: Escriba | E76: F | F76: 36417 | G76: 6 | H76: B | I76: 0 | K76: 40000 | L76: d008 | M76: Senior Engineer | N76: =IF(AND( Table15[[#This Row],[Salary]] >= 80000, OR(Table15[[#This Row],[Last_performance_rating]] = "C", Table15[[#This Row],[Last_performance_rating]] = "PIP")) = TRUE, 1, 0) -> 0
A77: 10047 | B77: 19174 | C77: Zvonko | D77: Nyanchama | E77: M | F77: 32598 | G77: 10 | H77: C | I77: 1 | J77: 33351 | K77: 54982 | L77: d004 | M77: Senior Engineer | N77: =IF(AND( Table15[[#This Row],[Salary]] >= 80000, OR(Table15[[#This Row],[Last_performance_rating]] = "C", Table15[[#This Row],[Last_performance_rating]] = "PIP")) = TRUE, 1, 0) -> 0
A78: 10048 | B78: 23203 | C78: Florian | D78: Syrotiuk | E78: M | F78: 31102 | G78: 9 | H78: B | I78: 0 | K78: 40000 | L78: d005 | M78: Engineer | N78: =IF(AND( Table15[[#This Row],[Salary]] >= 80000, OR(Table15[[#This Row],[Last_performance_rating]] = "C", Table15[[#This Row],[Last_performance_rating]] = "PIP")) = TRUE, 1, 0) -> 0
A79: 214555 | B79: 22197 | C79: Nechama | D79: Copas | E79: F | F79: 32077 | G79: 8 | H79: A | I79: 0 | K79: 40000 | L79: d005 | M79: Senior Engineer | N79: =IF(AND( Table15[[#This Row],[Salary]] >= 80000, OR(Table15[[#This Row],[Last_performance_rating]] = "C", Table15[[#This Row],[Last_performance_rating]] = "PIP")) = TRUE, 1, 0) -> 0
A80: 10049 | B80: 22395 | C80: Basil | D80: Tramer | E80: F | F80: 33728 | G80: 3 | H80: B | I80: 0 | K80: 40000 | L80: d009 | M80: Staff | N80: =IF(AND( Table15[[#This Row],[Salary]] >= 80000, OR(Table15[[#This Row],[Last_performance_rating]] = "C", Table15[[#This Row],[Last_performance_rating]] = "PIP")) = TRUE, 1, 0) -> 0
A81: 10050 | B81: 21326 | C81: Yinghua | D81: Dredge | E81: M | F81: 33232 | G81: 6 | H81: C | I81: 0 | K81: 74366 | L81: d002 | M81: Staff | N81: =IF(AND( Table15[[#This Row],[Salary]] >= 80000, OR(Table15[[#This Row],[Last_performance_rating]] = "C", Table15[[#This Row],[Last_performance_rating]] = "PIP")) = TRUE, 1, 0) -> 0
A82: 10050 | B82: 21326 | C82: Yinghua | D82: Dredge | E82: M | F82: 33232 | G82: 6 | H82: C | I82: 0 | K82: 74366 | L82: d007 | M82: Staff | N82: =IF(AND( Table15[[#This Row],[Salary]] >= 80000, OR(Table15[[#This Row],[Last_performance_rating]] = "C", Table15[[#This Row],[Last_performance_rating]] = "PIP")) = TRUE, 1, 0) -> 0
A83: 229010 | B83: 22597 | C83: Mark | D83: Cappelli | E83: M | F83: 33000 | G83: 9 | H83: B | I83: 0 | K83: 40000 | L83: d003 | M83: Staff | N83: =IF(AND( Table15[[#This Row],[Salary]] >= 80000, OR(Table15[[#This Row],[Last_performance_rating]] = "C", Table15[[#This Row],[Last_performance_rating]] = "PIP")) = TRUE, 1, 0) -> 0
A84: 10051 | B84: 19568 | C84: Hidefumi | D84: Caine | E84: M | F84: 33892 | G84: 2 | H84: A | I84: 0 | K84: 48817 | L84: d004 | M84: Senior Engineer | N84: =IF(AND( Table15[[#This Row],[Salary]] >= 80000, OR(Table15[[#This Row],[Last_performance_rating]] = "C", Table15[[#This Row],[Last_performance_rating]] = "PIP")) = TRUE, 1, 0) -> 0
A85: 35916 | B85: 19586 | C85: Wonhee | D85: Talmon | E85: F | F85: 31126 | G85: 1 | H85: A | I85: 0 | K85: 40000 | L85: d005 | M85: Senior Engineer | N85: =IF(AND( Table15[[#This Row],[Salary]] >= 80000, OR(Table15[[#This Row],[Last_performance_rating]] = "C", Table15[[#This Row],[Last_performance_rating]] = "PIP")) = TRUE, 1, 0) -> 0
A86: 10052 | B86: 22338 | C86: Heping | D86: Nitsch | E86: M | F86: 32284 | G86: 5 | H86: B | I86: 0 | K86: 57212 | L86: d008 | M86: Staff | N86: =IF(AND( Table15[[#This Row],[Salary]] >= 80000, OR(Table15[[#This Row],[Last_performance_rating]] = "C", Table15[[#This Row],[Last_performance_rating]] = "PIP")) = TRUE, 1, 0) -> 0
A87: 10053 | B87: 19980 | C87: Sanjiv | D87: Zschoche | E87: F | F87: 31447 | G87: 4 | H87: B | I87: 0 | K87: 67854 | L87: d007 | M87: Senior Staff | N87: =IF(AND( Table15[[#This Row],[Salary]] >= 80000, OR(Table15[[#This Row],[Last_performance_rating]] = "C", Table15[[#This Row],[Last_performance_rating]] = "PIP")) = TRUE, 1, 0) -> 0
A88: 61583 | B88: 20975 | C88: Ziva | D88: Vecchi | E88: M | F88: 31596 | G88: 6 | H88: B | I88: 0 | K88: 50801 | L88: d005 | M88: Senior Engineer | N88: =IF(AND( Table15[[#This Row],[Salary]] >= 80000, OR(Table15[[#This Row],[Last_performance_rating]] = "C", Table15[[#This Row],[Last_performance_rating]] = "PIP")) = TRUE, 1, 0) -> 0
A89: 10054 | B89: 20914 | C89: Mayumi | D89: Schueller | E89: M | F89: 34771 | G89: 8 | H89: A | I89: 0 | K89: 40000 | L89: d003 | M89: Staff | N89: =IF(AND( Table15[[#This Row],[Salary]] >= 80000, OR(Table15[[#This Row],[Last_performance_rating]] = "C", Table15[[#This Row],[Last_performance_rating]] = "PIP")) = TRUE, 1, 0) -> 0
... A101: 10061 | B101: 22938 | C101: Tse | D101: Herber | E101: M | F101: 31307 | G101: 1 | H101: B | I101: 0 | K101: 68577 | L101: d007 | M101: Senior Staff | N101: =IF(AND( Table15[[#This Row],[Salary]] >= 80000, OR(Table15[[#This Row],[Last_performance_rating]] = "C", Table15[[#This Row],[Last_performance_rating]] = "PIP")) = TRUE, 1, 0) -> 0
A102: 10062 | B102: 22587 | C102: Anoosh | D102: Peyn | E102: M | F102: 33480 | G102: 7 | H102: B | I102: 1 | J102: 34016 | K102: 55685 | L102: d005 | M102: Senior Engineer | N102: =IF(AND( Table15[[#This Row],[Salary]] >= 80000, OR(Table15[[#This Row],[Last_performance_rating]] = "C", Table15[[#This Row],[Last_performance_rating]] = "PIP")) = TRUE, 1, 0) -> 0
A103: 35270 | B103: 19361 | C103: Masali | D103: Bakhtari | E103: M | F103: 33274 | G103: 4 | H103: A | I103: 0 | K103: 40338 | L103: d004 | M103: Technique Leader | N103: =IF(AND( Table15[[#This Row],[Salary]] >= 80000, OR(Table15[[#This Row],[Last_performance_rating]] = "C", Table15[[#This Row],[Last_performance_rating]] = "PIP")) = TRUE, 1, 0) -> 0
A104: 10063 | B104: 19212 | C104: Gino | D104: Leonhardt | E104: F | F104: 32606 | G104: 1 | H104: A | I104: 0 | K104: 40000 | L104: d004 | M104: Senior Engineer | N104: =IF(AND( Table15[[#This Row],[Salary]] >= 80000, OR(Table15[[#This Row],[Last_performance_rating]] = "C", Table15[[#This Row],[Last_performance_rating]] = "PIP")) = TRUE, 1, 0) -> 0
A105: 10064 | B105: 21647 | C105: Udi | D105: Jansch | E105: M | F105: 31371 | G105: 2 | H105: A | I105: 0 | K105: 40000 | L105: d008 | M105: Staff | N105: =IF(AND( Table15[[#This Row],[Salary]] >= 80000, OR(Table15[[#This Row],[Last_performance_rating]] = "C", Table15[[#This Row],[Last_performance_rating]] = "PIP")) = TRUE, 1, 0) -> 0
A106: 105597 | B106: 20681 | C106: Christfried | D106: Kabayashi | E106: M | F106: 31908 | G106: 2 | H106: A | I106: 0 | K106: 43841 | L106: d003 | M106: Senior Staff | N106: =IF(AND( Table15[[#This Row],[Salary]] >= 80000, OR(Table15[[#This Row],[Last_performance_rating]] = "C", Table15[[#This Row],[Last_performance_rating]] = "PIP")) = TRUE, 1, 0) -> 0
A107: 10065 | B107: 23115 | C107: Satosi | D107: Awdeh | E107: M | F107: 32281 | G107: 5 | H107: B | I107: 0 | K107: 40000 | L107: d005 | M107: Engineer | N107: =IF(AND( Table15[[#This Row],[Salary]] >= 80000, OR(Table15[[#This Row],[Last_performance_rating]] = "C", Table15[[#This Row],[Last_performance_rating]] = "PIP")) = TRUE, 1, 0) -> 0
A108: 10066 | B108: 19311 | C108: Kwee | D108: Schusler | E108: M | F108: 31469 | G108: 1 | H108: PIP | I108: 0 | K108: 69736 | L108: d005 | M108: Senior Engineer | N108: =IF(AND( Table15[[#This Row],[Salary]] >= 80000, OR(Table15[[#This Row],[Last_performance_rating]] = "C", Table15[[#This Row],[Last_performance_rating]] = "PIP")) = TRUE, 1, 0) -> 0
A109: 244689 | B109: 20558 | C109: Urs | D109: Saoudi | E109: M | F109: 33483 | G109: 7 | H109: B | I109: 0 | K109: 40000 | L109: d001 | M109: Staff | N109: =IF(AND( Table15[[#This Row],[Salary]] >= 80000, OR(Table15[[#This Row],[Last_performance_rating]] = "C", Table15[[#This Row],[Last_performance_rating]] = "PIP")) = TRUE, 1, 0) -> 0
A110: 244689 | B110: 20558 | C110: Urs | D110: Saoudi | E110: M | F110: 33483 | G110: 7 | H110: B | I110: 0 | K110: 40000 | L110: d003 | M110: Staff | N110: =IF(AND( Table15[[#This Row],[Salary]] >= 80000, OR(Table15[[#This Row],[Last_performance_rating]] = "C", Table15[[#This Row],[Last_performance_rating]] = "PIP")) = TRUE, 1, 0) -> 0
A111: 10067 | B111: 19366 | C111: Claudi | D111: Stavenow | E111: M | F111: 31840 | G111: 2 | H111: C | I111: 0 | K111: 44642 | L111: d006 | M111: Senior Engineer | N111: =IF(AND( Table15[[#This Row],[Salary]] >= 80000, OR(Table15[[#This Row],[Last_performance_rating]] = "C", Table15[[#This Row],[Last_performance_rating]] = "PIP")) = TRUE, 1, 0) -> 0
A112: 10068 | B112: 22976 | C112: Charlene | D112: Brattka | E112: M | F112: 31996 | G112: 6 | H112: A | I112: 0 | K112: 87964 | L112: d007 | M112: Staff | N112: =IF(AND( Table15[[#This Row],[Salary]] >= 80000, OR(Table15[[#This Row],[Last_performance_rating]] = "C", Table15[[#This Row],[Last_performance_rating]] = "PIP")) = TRUE, 1, 0) -> 0
A113: 48885 | B113: 21425 | C113: Phuoc | D113: Antonisse | E113: M | F113: 34018 | G113: 9 | H113: B | I113: 0 | K113: 55736 | L113: d005 | M113: Senior Engineer | N113: =IF(AND( Table15[[#This Row],[Salary]] >= 80000, OR(Table15[[#This Row],[Last_performance_rating]] = "C", Table15[[#This Row],[Last_performance_rating]] = "PIP")) = TRUE, 1, 0) -> 0
A114: 10069 | B114: 22165 | C114: Margareta | D114: Bierman | E114: F | F114: 32817 | G114: 10 | H114: A | I114: 0 | K114: 67932 | L114: d004 | M114: Technique Leader | N114: =IF(AND( Table15[[#This Row],[Salary]] >= 80000, OR(Table15[[#This Row],[Last_performance_rating]] = "C", Table15[[#This Row],[Last_performance_rating]] = "PIP")) = TRUE, 1, 0) -> 0
... A116: 10070 | B116: 20321 | C116: Reuven | D116: Garigliano | E116: M | F116: 31334 | G116: 7 | H116: A | I116: 0 | K116: 55999 | L116: d008 | M116: Technique Leader | N116: =IF(AND( Table15[[#This Row],[Salary]] >= 80000, OR(Table15[[#This Row],[Last_performance_rating]] = "C", Table15[[#This Row],[Last_performance_rating]] = "PIP")) = TRUE, 1, 0) -> 0
A117: 244492 | B117: 21327 | C117: Shaunak | D117: Pettit | E117: M | F117: 34534 | G117: 3 | H117: C | I117: 1 | J117: 36844 | K117: 63685 | L117: d005 | M117: Senior Engineer | N117: =IF(AND( Table15[[#This Row],[Salary]] >= 80000, OR(Table15[[#This Row],[Last_performance_rating]] = "C", Table15[[#This Row],[Last_performance_rating]] = "PIP")) = TRUE, 1, 0) -> 0
A118: 10071 | B118: 21206 | C118: Hisao | D118: Lipner | E118: M | F118: 32051 | G118: 4 | H118: B | I118: 0 | K118: 40000 | L118: d003 | M118: Staff | N118: =IF(AND( Table15[[#This Row],[Salary]] >= 80000, OR(Table15[[#This Row],[Last_performance_rating]] = "C", Table15[[#This Row],[Last_performance_rating]] = "PIP")) = TRUE, 1, 0) -> 0
A119: 215615 | B119: 20864 | C119: Bader | D119: Chinal | E119: F | F119: 32881 | G119: 10 | H119: C | I119: 0 | K119: 40000 | L119: d004 | M119: Engineer | N119: =IF(AND( Table15[[#This Row],[Salary]] >= 80000, OR(Table15[[#This Row],[Last_performance_rating]] = "C", Table15[[#This Row],[Last_performance_rating]] = "PIP")) = TRUE, 1, 0) -> 0
A120: 215615 | B120: 20864 | C120: Bader | D120: Chinal | E120: F | F120: 32881 | G120: 10 | H120: C | I120: 0 | K120: 40000 | L120: d006 | M120: Engineer | N120: =IF(AND( Table15[[#This Row],[Salary]] >= 80000, OR(Table15[[#This Row],[Last_performance_rating]] = "C", Table15[[#This Row],[Last_performance_rating]] = "PIP")) = TRUE, 1, 0) -> 0
A121: 10072 | B121: 19129 | C121: Hironoby | D121: Sidou | E121: F | F121: 32345 | G121: 8 | H121: B | I121: 0 | K121: 40000 | L121: d005 | M121: Senior Engineer | N121: =IF(AND( Table15[[#This Row],[Salary]] >= 80000, OR(Table15[[#This Row],[Last_performance_rating]] = "C", Table15[[#This Row],[Last_performance_rating]] = "PIP")) = TRUE, 1, 0) -> 0
A122: 10073 | B122: 19778 | C122: Shir | D122: McClurg | E122: M | F122: 33573 | G122: 5 | H122: C | I122: 0 | K122: 56473 | L122: d006 | M122: Engineer | N122: =IF(AND( Table15[[#This Row],[Salary]] >= 80000, OR(Table15[[#This Row],[Last_performance_rating]] = "C", Table15[[#This Row],[Last_performance_rating]] = "PIP")) = TRUE, 1, 0) -> 0
A123: 95280 | B123: 21960 | C123: Owen | D123: Hiraishi | E123: F | F123: 31266 | G123: 10 | H123: S | I123: 0 | K123: 40000 | L123: d004 | M123: Senior Engineer | N123: =IF(AND( Table15[[#This Row],[Salary]] >= 80000, OR(Table15[[#This Row],[Last_performance_rating]] = "C", Table15[[#This Row],[Last_performance_rating]] = "PIP")) = TRUE, 1, 0) -> 0
A124: 10074 | B124: 20329 | C124: Mokhtar | D124: Bernatsky | E124: F | F124: 33098 | G124: 8 | H124: PIP | I124: 1 | J124: 34841 | K124: 61714 | L124: d005 | M124: Technique Leader | N124: =IF(AND( Table15[[#This Row],[Salary]] >= 80000, OR(Table15[[#This Row],[Last_performance_rating]] = "C", Table15[[#This Row],[Last_performance_rating]] = "PIP")) = TRUE, 1, 0) -> 0
A125: 10075 | B125: 21984 | C125: Gao | D125: Dolinsky | E125: F | F125: 31855 | G125: 4 | H125: B | I125: 0 | K125: 43815 | L125: d005 | M125: Senior Engineer | N125: =IF(AND( Table15[[#This Row],[Salary]] >= 80000, OR(Table15[[#This Row],[Last_performance_rating]] = "C", Table15[[#This Row],[Last_performance_rating]] = "PIP")) = TRUE, 1, 0) -> 0
A126: 37473 | B126: 19059 | C126: Prasadram | D126: Valette | E126: M | F126: 34381 | G126: 3 | H126: PIP | I126: 0 | K126: 55963 | L126: d002 | M126: Staff | N126: =IF(AND( Table15[[#This Row],[Salary]] >= 80000, OR(Table15[[#This Row],[Last_performance_rating]] = "C", Table15[[#This Row],[Last_performance_rating]] = "PIP")) = TRUE, 1, 0) -> 0
A127: 10076 | B127: 19158 | C127: Erez | D127: Ritzmann | E127: F | F127: 31237 | G127: 9 | H127: B | I127: 0 | K127: 47319 | L127: d005 | M127: Senior Engineer | N127: =IF(AND( Table15[[#This Row],[Salary]] >= 80000, OR(Table15[[#This Row],[Last_performance_rating]] = "C", Table15[[#This Row],[Last_performance_rating]] = "PIP")) = TRUE, 1, 0) -> 0
...

Sheet Emp
A1: Emp_Id | B1: DOB | C1: first_name | D1: last_name | E1: Gender | F1: DoJ | G1: no_of_projects | H1: Last_performance_rating | I1: Left? | J1: last_date | K1: Salary | L1: Dept_Id | M1: Title | N1: DepName
A2: 10001 | B2: 9/2/1953 | C2: Georgi | D2: Facello | E2: M | F2: 6/26/1986 | G2: 9 | H2: C | I2: 1 | J2: 7/30/1994 | K2: 60117 | L2: d005 | M2: Senior Engineer | N2: =INDEX(Table3[#All], MATCH(Table13[[#This Row],[Dept_Id]], Table3[[#All],[Dept_Id]], 0), 1) -> Development
A3: 10003 | B3: 12/3/1959 | C3: Parto | D3: Bamford | E3: M | F3: 8/28/1986 | G3: 1 | H3: C | I3: 0 | K3: 40006 | L3: d004 | M3: Senior Engineer | N3: =INDEX(Table3[#All], MATCH(Table13[[#This Row],[Dept_Id]], Table3[[#All],[Dept_Id]], 0), 1) -> Production
A4: 10004 | B4: 5/1/1954 | C4: Chirstian | D4: Koblick | E4: M | F4: 12/1/1986 | G4: 5 | H4: A | I4: 0 | K4: 40054 | L4: d004 | M4: Senior Engineer | N4: =INDEX(Table3[#All], MATCH(Table13[[#This Row],[Dept_Id]], Table3[[#All],[Dept_Id]], 0), 1) -> Production
A5: 10006 | B5: 4/20/1953 | C5: Anneke | D5: Preusig | E5: F | F5: 6/2/1989 | G5: 10 | H5: B | I5: 0 | K5: 40000 | L5: d005 | M5: Senior Engineer | N5: =INDEX(Table3[#All], MATCH(Table13[[#This Row],[Dept_Id]], Table3[[#All],[Dept_Id]], 0), 1) -> Development
A6: 10002 | B6: 6/2/1964 | C6: Bezalel | D6: Simmel | E6: F | F6: 11/21/1985 | G6: 8 | H6: B | I6: 0 | K6: 65828 | L6: d007 | M6: Staff | N6: =INDEX(Table3[#All], MATCH(Table13[[#This Row],[Dept_Id]], Table3[[#All],[Dept_Id]], 0), 1) -> Sales
A7: 10005 | B7: 1/21/1955 | C7: Kyoichi | D7: Maliniak | E7: M | F7: 9/12/1989 | G7: 6 | H7: A | I7: 0 | K7: 78228 | L7: d003 | M7: Staff | N7: =INDEX(Table3[#All], MATCH(Table13[[#This Row],[Dept_Id]], Table3[[#All],[Dept_Id]], 0), 1) -> Human Resources
A8: 421786 | B8: 9/28/1957 | C8: Xiong | D8: Verhoeff | E8: M | F8: 11/26/1987 | G8: 2 | H8: C | I8: 0 | K8: 40000 | L8: d003 | M8: Staff | N8: =INDEX(Table3[#All], MATCH(Table13[[#This Row],[Dept_Id]], Table3[[#All],[Dept_Id]], 0), 1) -> Human Resources
A9: 57444 | B9: 1/30/1958 | C9: Berry | D9: Babb | E9: F | F9: 3/21/1992 | G9: 9 | H9: A | I9: 0 | K9: 48973 | L9: d004 | M9: Engineer | N9: =INDEX(Table3[#All], MATCH(Table13[[#This Row],[Dept_Id]], Table3[[#All],[Dept_Id]], 0), 1) -> Production
A10: 10007 | B10: 5/23/1957 | C10: Tzvetan | D10: Zielinski | E10: F | F10: 2/10/1989 | G10: 6 | H10: B | I10: 1 | J10: 9/18/2002 | K10: 56724 | L10: d008 | M10: Staff | N10: =INDEX(Table3[#All], MATCH(Table13[[#This Row],[Dept_Id]], Table3[[#All],[Dept_Id]], 0), 1) -> Research
A11: 10008 | B11: 2/19/1958 | C11: Saniya | D11: Kalloufi | E11: M | F11: 9/15/1994 | G11: 9 | H11: C | I11: 0 | K11: 46671 | L11: d005 | M11: Assistant Engineer | N11: =INDEX(Table3[#All], MATCH(Table13[[#This Row],[Dept_Id]], Table3[[#All],[Dept_Id]], 0), 1) -> Development
A12: 282238 | B12: 10/28/1952 | C12: Abdelkader | D12: Baumann | E12: F | F12: 1/18/1991 | G12: 6 | H12: B | I12: 0 | K12: 40000 | L12: d006 | M12: Senior Engineer | N12: =INDEX(Table3[#All], MATCH(Table13[[#This Row],[Dept_Id]], Table3[[#All],[Dept_Id]], 0), 1) -> Quality Management
A13: 10009 | B13: 4/19/1952 | C13: Sumant | D13: Peac | E13: F | F13: 2/18/1985 | G13: 8 | H13: B | I13: 0 | K13: 60929 | L13: d006 | M13: Senior Engineer | N13: =INDEX(Table3[#All], MATCH(Table13[[#This Row],[Dept_Id]], Table3[[#All],[Dept_Id]], 0), 1) -> Quality Management
A14: 10010 | B14: 6/1/1963 | C14: Duangkaew | D14: Piveteau | E14: F | F14: 8/24/1989 | G14: 4 | H14: A | I14: 0 | K14: 72488 | L14: d004 | M14: Engineer | N14: =INDEX(Table3[#All], MATCH(Table13[[#This Row],[Dept_Id]], Table3[[#All],[Dept_Id]], 0), 1) -> Production
A15: 10010 | B15: 6/1/1963 | C15: Duangkaew | D15: Piveteau | E15: F | F15: 8/24/1989 | G15: 4 | H15: A | I15: 0 | K15: 72488 | L15: d006 | M15: Engineer | N15: =INDEX(Table3[#All], MATCH(Table13[[#This Row],[Dept_Id]], Table3[[#All],[Dept_Id]], 0), 1) -> Quality Management
A16: 263976 | B16: 10/30/1959 | C16: Eran | D16: Cusworth | E16: M | F16: 11/14/1986 | G16: 8 | H16: B | I16: 1 | J16: 8/21/1993 | K16: 40000 | L16: d006 | M16: Senior Engineer | N16: =INDEX(Table3[#All], MATCH(Table13[[#This Row],[Dept_Id]], Table3[[#All],[Dept_Id]], 0), 1) -> Quality Management
A17: 10011 | B17: 11/7/1953 | C17: Mary | D17: Sluis | E17: F | F17: 1/22/1990 | G17: 6 | H17: C | I17: 0 | K17: 42365 | L17: d009 | M17: Staff | N17: =INDEX(Table3[#All], MATCH(Table13[[#This Row],[Dept_Id]], Table3[[#All],[Dept_Id]], 0), 1) -> Customer Service
A18: 273487 | B18: 4/14/1957 | C18: Christoph | D18: Parfitt | E18: M | F18: 6/28/1991 | G18: 10 | H18: A | I18: 0 | K18: 56087 | L18: d003 | M18: Staff | N18: =INDEX(Table3[#All], MATCH(Table13[[#This Row],[Dept_Id]], Table3[[#All],[Dept_Id]], 0), 1) -> Human Resources
A19: 10012 | B19: 10/4/1960 | C19: Patricio | D19: Bridgland | E19: M | F19: 12/18/1992 | G19: 3 | H19: A | I19: 0 | K19: 40000 | L19: d005 | M19: Senior Engineer | N19: =INDEX(Table3[#All], MATCH(Table13[[#This Row],[Dept_Id]], Table3[[#All],[Dept_Id]], 0), 1) -> Development
A20: 10013 | B20: 6/7/1963 | C20: Eberhardt | D20: Terkki | E20: M | F20: 10/20/1985 | G20: 6 | H20: C | I20: 0 | K20: 40000 | L20: d003 | M20: Senior Staff | N20: =INDEX(Table3[#All], MATCH(Table13[[#This Row],[Dept_Id]], Table3[[#All],[Dept_Id]], 0), 1) -> Human Resources
A21: 461591 | B21: 11/17/1964 | C21: Xudong | D21: Samarati | E21: M | F21: 11/13/1985 | G21: 2 | H21: A | I21: 1 | J21: 8/21/1994 | K21: 40000 | L21: d002 | M21: Senior Staff | N21: =INDEX(Table3[#All], MATCH(Table13[[#This Row],[Dept_Id]], Table3[[#All],[Dept_Id]], 0), 1) -> Finance
A22: 10014 | B22: 2/12/1956 | C22: Berni | D22: Genin | E22: M | F22: 3/11/1987 | G22: 9 | H22: B | I22: 0 | K22: 46168 | L22: d005 | M22: Engineer | N22: =INDEX(Table3[#All], MATCH(Table13[[#This Row],[Dept_Id]], Table3[[#All],[Dept_Id]], 0), 1) -> Development
A23: 10015 | B23: 8/19/1959 | C23: Guoxiang | D23: Nooteboom | E23: M | F23: 7/2/1987 | G23: 4 | H23: B | I23: 0 | K23: 40000 | L23: d008 | M23: Senior Staff | N23: =INDEX(Table3[#All], MATCH(Table13[[#This Row],[Dept_Id]], Table3[[#All],[Dept_Id]], 0), 1) -> Research
A24: 10016 | B24: 5/2/1961 | C24: Kazuhito | D24: Cappelletti | E24: M | F24: 1/27/1995 | G24: 5 | H24: C | I24: 0 | K24: 70889 | L24: d007 | M24: Staff | N24: =INDEX(Table3[#All], MATCH(Table13[[#This Row],[Dept_Id]], Table3[[#All],[Dept_Id]], 0), 1) -> Sales
A25: 10017 | B25: 7/6/1958 | C25: Cristinel | D25: Bouloucos | E25: F | F25: 8/3/1993 | G25: 10 | H25: A | I25: 0 | K25: 71380 | L25: d001 | M25: Staff | N25: =INDEX(Table3[#All], MATCH(Table13[[#This Row],[Dept_Id]], Table3[[#All],[Dept_Id]], 0), 1) -> Marketing
A26: 219881 | B26: 4/24/1956 | C26: Kwangyoen | D26: Speek | E26: F | F26: 2/14/1993 | G26: 6 | H26: B | I26: 0 | K26: 40000 | L26: d009 | M26: Senior Staff | N26: =INDEX(Table3[#All], MATCH(Table13[[#This Row],[Dept_Id]], Table3[[#All],[Dept_Id]], 0), 1) -> Customer Service
A27: 10018 | B27: 6/19/1954 | C27: Kazuhide | D27: Peha | E27: F | F27: 4/3/1987 | G27: 4 | H27: B | I27: 0 | K27: 55881 | L27: d004 | M27: Senior Engineer | N27: =INDEX(Table3[#All], MATCH(Table13[[#This Row],[Dept_Id]], Table3[[#All],[Dept_Id]], 0), 1) -> Production
A28: 10018 | B28: 6/19/1954 | C28: Kazuhide | D28: Peha | E28: F | F28: 4/3/1987 | G28: 4 | H28: B | I28: 0 | K28: 55881 | L28: d005 | M28: Senior Engineer | N28: =INDEX(Table3[#All], MATCH(Table13[[#This Row],[Dept_Id]], Table3[[#All],[Dept_Id]], 0), 1) -> Development
A29: 29920 | B29: 12/31/1961 | C29: Shuichi | D29: Tyugu | E29: F | F29: 1/17/1995 | G29: 1 | H29: PIP | I29: 0 | K29: 40000 | L29: d004 | M29: Engineer | N29: =INDEX(Table3[#All], MATCH(Table13[[#This Row],[Dept_Id]], Table3[[#All],[Dept_Id]], 0), 1) -> Production
A30: 10019 | B30: 1/23/1953 | C30: Lillian | D30: Haddadi | E30: M | F30: 4/30/1999 | G30: 4 | H30: B | I30: 0 | K30: 44276 | L30: d008 | M30: Staff | N30: =INDEX(Table3[#All], MATCH(Table13[[#This Row],[Dept_Id]], Table3[[#All],[Dept_Id]], 0), 1) -> Research
A31: 10020 | B31: 12/24/1952 | C31: Mayuko | D31: Warwick | E31: M | F31: 1/26/1991 | G31: 7 | H31: B | I31: 0 | K31: 40000 | L31: d004 | M31: Engineer | N31: =INDEX(Table3[#All], MATCH(Table13[[#This Row],[Dept_Id]], Table3[[#All],[Dept_Id]], 0), 1) -> Production
A32: 208153 | B32: 10/25/1961 | C32: Abdulah | D32: Lunn | E32: M | F32: 4/8/1989 | G32: 8 | H32: C | I32: 1 | J32: 8/2/2000 | K32: 50183 | L32: d005 | M32: Senior Engineer | N32: =INDEX(Table3[#All], MATCH(Table13[[#This Row],[Dept_Id]], Table3[[#All],[Dept_Id]], 0), 1) -> Development
A33: 10021 | B33: 2/20/1960 | C33: Ramzi | D33: Erde | E33: M | F33: 2/10/1988 | G33: 1 | H33: B | I33: 0 | K33: 55025 | L33: d005 | M33: Technique Leader | N33: =INDEX(Table3[#All], MATCH(Table13[[#This Row],[Dept_Id]], Table3[[#All],[Dept_Id]], 0), 1) -> Development
A34: 10022 | B34: 7/8/1952 | C34: Shahaf | D34: Famili | E34: M | F34: 8/22/1995 | G34: 9 | H34: B | I34: 1 | J34: 11/4/2005 | K34: 40000 | L34: d005 | M34: Engineer | N34: =INDEX(Table3[#All], MATCH(Table13[[#This Row],[Dept_Id]], Table3[[#All],[Dept_Id]], 0), 1) -> Development
A35: 13616 | B35: 8/30/1961 | C35: Perry | D35: Lorho | E35: F | F35: 8/3/1991 | G35: 7 | H35: C | I35: 0 | K35: 40000 | L35: d005 | M35: Senior Engineer | N35: =INDEX(Table3[#All], MATCH(Table13[[#This Row],[Dept_Id]], Table3[[#All],[Dept_Id]], 0), 1) -> Development
A36: 13616 | B36: 8/30/1961 | C36: Perry | D36: Lorho | E36: F | F36: 8/3/1991 | G36: 7 | H36: C | I36: 0 | K36: 40000 | L36: d008 | M36: Senior Engineer | N36: =INDEX(Table3[#All], MATCH(Table13[[#This Row],[Dept_Id]], Table3[[#All],[Dept_Id]], 0), 1) -> Research
A37: 10023 | B37: 9/29/1953 | C37: Bojan | D37: Montemayor | E37: F | F37: 12/17/1989 | G37: 8 | H37: A | I37: 0 | K37: 47883 | L37: d005 | M37: Engineer | N37: =INDEX(Table3[#All], MATCH(Table13[[#This Row],[Dept_Id]], Table3[[#All],[Dept_Id]], 0), 1) -> Development
A38: 10024 | B38: 9/5/1958 | C38: Suzette | D38: Pettey | E38: F | F38: 5/19/1997 | G38: 3 | H38: A | I38: 0 | K38: 83733 | L38: d004 | M38: Assistant Engineer | N38: =INDEX(Table3[#All], MATCH(Table13[[#This Row],[Dept_Id]], Table3[[#All],[Dept_Id]], 0), 1) -> Production
A39: 246449 | B39: 3/23/1958 | C39: Subbu | D39: Bultermann | E39: F | F39: 3/25/1988 | G39: 9 | H39: C | I39: 0 | K39: 87084 | L39: d007 | M39: Staff | N39: =INDEX(Table3[#All], MATCH(Table13[[#This Row],[Dept_Id]], Table3[[#All],[Dept_Id]], 0), 1) -> Sales
A40: 10025 | B40: 10/31/1958 | C40: Prasadram | D40: Heyers | E40: M | F40: 8/17/1987 | G40: 6 | H40: C | I40: 0 | K40: 40000 | L40: d005 | M40: Technique Leader | N40: =INDEX(Table3[#All], MATCH(Table13[[#This Row],[Dept_Id]], Table3[[#All],[Dept_Id]], 0), 1) -> Development
A41: 10026 | B41: 4/3/1953 | C41: Yongqiao | D41: Berztiss | E41: M | F41: 3/20/1995 | G41: 1 | H41: PIP | I41: 0 | K41: 47585 | L41: d004 | M41: Senior Engineer | N41: =INDEX(Table3[#All], MATCH(Table13[[#This Row],[Dept_Id]], Table3[[#All],[Dept_Id]], 0), 1) -> Production
A42: 21529 | B42: 5/19/1959 | C42: Bojan | D42: Zallocco | E42: M | F42: 10/14/1986 | G42: 7 | H42: C | I42: 0 | K42: 40000 | L42: d005 | M42: Engineer | N42: =INDEX(Table3[#All], MATCH(Table13[[#This Row],[Dept_Id]], Table3[[#All],[Dept_Id]], 0), 1) -> Development
A43: 10027 | B43: 7/10/1962 | C43: Divier | D43: Reistad | E43: F | F43: 7/7/1989 | G43: 10 | H43: B | I43: 0 | K43: 40000 | L43: d005 | M43: Senior Engineer | N43: =INDEX(Table3[#All], MATCH(Table13[[#This Row],[Dept_Id]], Table3[[#All],[Dept_Id]], 0), 1) -> Development
A44: 10028 | B44: 11/26/1963 | C44: Domenick | D44: Tempesti | E44: M | F44: 10/22/1991 | G44: 8 | H44: B | I44: 0 | K44: 48859 | L44: d005 | M44: Engineer | N44: =INDEX(Table3[#All], MATCH(Table13[[#This Row],[Dept_Id]], Table3[[#All],[Dept_Id]], 0), 1) -> Development
A45: 17934 | B45: 7/12/1963 | C45: Bilhanan | D45: Wuwongse | E45: M | F45: 10/6/1993 | G45: 7 | H45: C | I45: 0 | K45: 48795 | L45: d005 | M45: Technique Leader | N45: =INDEX(Table3[#All], MATCH(Table13[[#This Row],[Dept_Id]], Table3[[#All],[Dept_Id]], 0), 1) -> Development
A46: 10029 | B46: 12/13/1956 | C46: Otmar | D46: Herbst | E46: M | F46: 11/20/1985 | G46: 6 | H46: C | I46: 0 | K46: 63163 | L46: d004 | M46: Senior Engineer | N46: =INDEX(Table3[#All], MATCH(Table13[[#This Row],[Dept_Id]], Table3[[#All],[Dept_Id]], 0), 1) -> Production
... A49: 10030 | B49: 7/14/1958 | C49: Elvis | D49: Demeyer | E49: M | F49: 2/17/1994 | G49: 10 | H49: A | I49: 0 | K49: 66956 | L49: d004 | M49: Senior Engineer | N49: =INDEX(Table3[#All], MATCH(Table13[[#This Row],[Dept_Id]], Table3[[#All],[Dept_Id]], 0), 1) -> Production
A50: 10031 | B50: 1/27/1959 | C50: Karsten | D50: Joslin | E50: M | F50: 9/1/1991 | G50: 2 | H50: C | I50: 1 | J50: 8/3/1999 | K50: 40000 | L50: d005 | M50: Senior Engineer | N50: =INDEX(Table3[#All], MATCH(Table13[[#This Row],[Dept_Id]], Table3[[#All],[Dept_Id]], 0), 1) -> Development
A51: 239838 | B51: 12/11/1957 | C51: Naftali | D51: Dulli | E51: M | F51: 6/6/1993 | G51: 3 | H51: A | I51: 0 | K51: 57715 | L51: d004 | M51: Engineer | N51: =INDEX(Table3[#All], MATCH(Table13[[#This Row],[Dept_Id]], Table3[[#All],[Dept_Id]], 0), 1) -> Production
A52: 10032 | B52: 8/9/1960 | C52: Jeong | D52: Reistad | E52: F | F52: 6/20/1990 | G52: 9 | H52: C | I52: 0 | K52: 48426 | L52: d004 | M52: Senior Engineer | N52: =INDEX(Table3[#All], MATCH(Table13[[#This Row],[Dept_Id]], Table3[[#All],[Dept_Id]], 0), 1) -> Production
A53: 10033 | B53: 11/14/1956 | C53: Arif | D53: Merlo | E53: M | F53: 3/18/1987 | G53: 9 | H53: A | I53: 0 | K53: 51258 | L53: d006 | M53: Technique Leader | N53: =INDEX(Table3[#All], MATCH(Table13[[#This Row],[Dept_Id]], Table3[[#All],[Dept_Id]], 0), 1) -> Quality Management
A54: 240129 | B54: 8/11/1952 | C54: Roddy | D54: Karnin | E54: M | F54: 5/29/1985 | G54: 10 | H54: C | I54: 0 | K54: 43548 | L54: d006 | M54: Technique Leader | N54: =INDEX(Table3[#All], MATCH(Table13[[#This Row],[Dept_Id]], Table3[[#All],[Dept_Id]], 0), 1) -> Quality Management
A55: 10034 | B55: 12/29/1962 | C55: Bader | D55: Swan | E55: M | F55: 9/21/1988 | G55: 8 | H55: C | I55: 0 | K55: 47561 | L55: d007 | M55: Staff | N55: =INDEX(Table3[#All], MATCH(Table13[[#This Row],[Dept_Id]], Table3[[#All],[Dept_Id]], 0), 1) -> Sales
A56: 10035 | B56: 2/8/1953 | C56: Alain | D56: Chappelet | E56: M | F56: 9/5/1988 | G56: 6 | H56: B | I56: 0 | K56: 41538 | L56: d004 | M56: Senior Engineer | N56: =INDEX(Table3[#All], MATCH(Table13[[#This Row],[Dept_Id]], Table3[[#All],[Dept_Id]], 0), 1) -> Production
A57: 205246 | B57: 11/25/1958 | C57: Nevio | D57: Demizu | E57: F | F57: 5/18/1986 | G57: 8 | H57: B | I57: 0 | K57: 80252 | L57: d007 | M57: Senior Staff | N57: =INDEX(Table3[#All], MATCH(Table13[[#This Row],[Dept_Id]], Table3[[#All],[Dept_Id]], 0), 1) -> Sales
A58: 10036 | B58: 8/10/1959 | C58: Adamantios | D58: Portugali | E58: M | F58: 1/3/1992 | G58: 5 | H58: C | I58: 0 | K58: 42819 | L58: d003 | M58: Senior Staff | N58: =INDEX(Table3[#All], MATCH(Table13[[#This Row],[Dept_Id]], Table3[[#All],[Dept_Id]], 0), 1) -> Human Resources
A59: 10037 | B59: 7/22/1963 | C59: Pradeep | D59: Makrucki | E59: M | F59: 12/5/1990 | G59: 4 | H59: A | I59: 0 | K59: 40000 | L59: d005 | M59: Senior Engineer | N59: =INDEX(Table3[#All], MATCH(Table13[[#This Row],[Dept_Id]], Table3[[#All],[Dept_Id]], 0), 1) -> Development
A60: 10038 | B60: 7/20/1960 | C60: Huan | D60: Lortz | E60: M | F60: 9/20/1989 | G60: 5 | H60: A | I60: 0 | K60: 40000 | L60: d009 | M60: Staff | N60: =INDEX(Table3[#All], MATCH(Table13[[#This Row],[Dept_Id]], Table3[[#All],[Dept_Id]], 0), 1) -> Customer Service
A61: 10039 | B61: 10/1/1959 | C61: Alejandro | D61: Brender | E61: M | F61: 1/19/1988 | G61: 1 | H61: B | I61: 0 | K61: 40000 | L61: d003 | M61: Staff | N61: =INDEX(Table3[#All], MATCH(Table13[[#This Row],[Dept_Id]], Table3[[#All],[Dept_Id]], 0), 1) -> Human Resources
A62: 424270 | B62: 1/15/1963 | C62: Kellyn | D62: Yoshizawa | E62: F | F62: 5/8/1995 | G62: 8 | H62: A | I62: 0 | K62: 60678 | L62: d002 | M62: Staff | N62: =INDEX(Table3[#All], MATCH(Table13[[#This Row],[Dept_Id]], Table3[[#All],[Dept_Id]], 0), 1) -> Finance
... A76: 104639 | B76: 6/19/1960 | C76: Theron | D76: Escriba | E76: F | F76: 9/14/1999 | G76: 6 | H76: B | I76: 0 | K76: 40000 | L76: d008 | M76: Senior Engineer | N76: =INDEX(Table3[#All], MATCH(Table13[[#This Row],[Dept_Id]], Table3[[#All],[Dept_Id]], 0), 1) -> Research
A77: 10047 | B77: 6/29/1952 | C77: Zvonko | D77: Nyanchama | E77: M | F77: 3/31/1989 | G77: 10 | H77: C | I77: 1 | J77: 4/23/1991 | K77: 54982 | L77: d004 | M77: Senior Engineer | N77: =INDEX(Table3[#All], MATCH(Table13[[#This Row],[Dept_Id]], Table3[[#All],[Dept_Id]], 0), 1) -> Production
A78: 10048 | B78: 7/11/1963 | C78: Florian | D78: Syrotiuk | E78: M | F78: 2/24/1985 | G78: 9 | H78: B | I78: 0 | K78: 40000 | L78: d005 | M78: Engineer | N78: =INDEX(Table3[#All], MATCH(Table13[[#This Row],[Dept_Id]], Table3[[#All],[Dept_Id]], 0), 1) -> Development
A79: 214555 | B79: 10/8/1960 | C79: Nechama | D79: Copas | E79: F | F79: 10/27/1987 | G79: 8 | H79: A | I79: 0 | K79: 40000 | L79: d005 | M79: Senior Engineer | N79: =INDEX(Table3[#All], MATCH(Table13[[#This Row],[Dept_Id]], Table3[[#All],[Dept_Id]], 0), 1) -> Development
A80: 10049 | B80: 4/24/1961 | C80: Basil | D80: Tramer | E80: F | F80: 5/4/1992 | G80: 3 | H80: B | I80: 0 | K80: 40000 | L80: d009 | M80: Staff | N80: =INDEX(Table3[#All], MATCH(Table13[[#This Row],[Dept_Id]], Table3[[#All],[Dept_Id]], 0), 1) -> Customer Service
A81: 10050 | B81: 5/21/1958 | C81: Yinghua | D81: Dredge | E81: M | F81: 12/25/1990 | G81: 6 | H81: C | I81: 0 | K81: 74366 | L81: d002 | M81: Staff | N81: =INDEX(Table3[#All], MATCH(Table13[[#This Row],[Dept_Id]], Table3[[#All],[Dept_Id]], 0), 1) -> Finance
A82: 10050 | B82: 5/21/1958 | C82: Yinghua | D82: Dredge | E82: M | F82: 12/25/1990 | G82: 6 | H82: C | I82: 0 | K82: 74366 | L82: d007 | M82: Staff | N82: =INDEX(Table3[#All], MATCH(Table13[[#This Row],[Dept_Id]], Table3[[#All],[Dept_Id]], 0), 1) -> Sales
A83: 229010 | B83: 11/12/1961 | C83: Mark | D83: Cappelli | E83: M | F83: 5/7/1990 | G83: 9 | H83: B | I83: 0 | K83: 40000 | L83: d003 | M83: Staff | N83: =INDEX(Table3[#All], MATCH(Table13[[#This Row],[Dept_Id]], Table3[[#All],[Dept_Id]], 0), 1) -> Human Resources
A84: 10051 | B84: 7/28/1953 | C84: Hidefumi | D84: Caine | E84: M | F84: 10/15/1992 | G84: 2 | H84: A | I84: 0 | K84: 48817 | L84: d004 | M84: Senior Engineer | N84: =INDEX(Table3[#All], MATCH(Table13[[#This Row],[Dept_Id]], Table3[[#All],[Dept_Id]], 0), 1) -> Production
A85: 35916 | B85: 8/15/1953 | C85: Wonhee | D85: Talmon | E85: F | F85: 3/20/1985 | G85: 1 | H85: A | I85: 0 | K85: 40000 | L85: d005 | M85: Senior Engineer | N85: =INDEX(Table3[#All], MATCH(Table13[[#This Row],[Dept_Id]], Table3[[#All],[Dept_Id]], 0), 1) -> Development
A86: 10052 | B86: 2/26/1961 | C86: Heping | D86: Nitsch | E86: M | F86: 5/21/1988 | G86: 5 | H86: B | I86: 0 | K86: 57212 | L86: d008 | M86: Staff | N86: =INDEX(Table3[#All], MATCH(Table13[[#This Row],[Dept_Id]], Table3[[#All],[Dept_Id]], 0), 1) -> Research
A87: 10053 | B87: 9/13/1954 | C87: Sanjiv | D87: Zschoche | E87: F | F87: 2/4/1986 | G87: 4 | H87: B | I87: 0 | K87: 67854 | L87: d007 | M87: Senior Staff | N87: =INDEX(Table3[#All], MATCH(Table13[[#This Row],[Dept_Id]], Table3[[#All],[Dept_Id]], 0), 1) -> Sales
A88: 61583 | B88: 6/4/1957 | C88: Ziva | D88: Vecchi | E88: M | F88: 7/3/1986 | G88: 6 | H88: B | I88: 0 | K88: 50801 | L88: d005 | M88: Senior Engineer | N88: =INDEX(Table3[#All], MATCH(Table13[[#This Row],[Dept_Id]], Table3[[#All],[Dept_Id]], 0), 1) -> Development
A89: 10054 | B89: 4/4/1957 | C89: Mayumi | D89: Schueller | E89: M | F89: 3/13/1995 | G89: 8 | H89: A | I89: 0 | K89: 40000 | L89: d003 | M89: Staff | N89: =INDEX(Table3[#All], MATCH(Table13[[#This Row],[Dept_Id]], Table3[[#All],[Dept_Id]], 0), 1) -> Human Resources
... A101: 10061 | B101: 10/19/1962 | C101: Tse | D101: Herber | E101: M | F101: 9/17/1985 | G101: 1 | H101: B | I101: 0 | K101: 68577 | L101: d007 | M101: Senior Staff | N101: =INDEX(Table3[#All], MATCH(Table13[[#This Row],[Dept_Id]], Table3[[#All],[Dept_Id]], 0), 1) -> Sales
A102: 10062 | B102: 11/2/1961 | C102: Anoosh | D102: Peyn | E102: M | F102: 8/30/1991 | G102: 7 | H102: B | I102: 1 | J102: 2/16/1993 | K102: 55685 | L102: d005 | M102: Senior Engineer | N102: =INDEX(Table3[#All], MATCH(Table13[[#This Row],[Dept_Id]], Table3[[#All],[Dept_Id]], 0), 1) -> Development
A103: 35270 | B103: 1/2/1953 | C103: Masali | D103: Bakhtari | E103: M | F103: 2/5/1991 | G103: 4 | H103: A | I103: 0 | K103: 40338 | L103: d004 | M103: Technique Leader | N103: =INDEX(Table3[#All], MATCH(Table13[[#This Row],[Dept_Id]], Table3[[#All],[Dept_Id]], 0), 1) -> Production
A104: 10063 | B104: 8/6/1952 | C104: Gino | D104: Leonhardt | E104: F | F104: 4/8/1989 | G104: 1 | H104: A | I104: 0 | K104: 40000 | L104: d004 | M104: Senior Engineer | N104: =INDEX(Table3[#All], MATCH(Table13[[#This Row],[Dept_Id]], Table3[[#All],[Dept_Id]], 0), 1) -> Production
A105: 10064 | B105: 4/7/1959 | C105: Udi | D105: Jansch | E105: M | F105: 11/20/1985 | G105: 2 | H105: A | I105: 0 | K105: 40000 | L105: d008 | M105: Staff | N105: =INDEX(Table3[#All], MATCH(Table13[[#This Row],[Dept_Id]], Table3[[#All],[Dept_Id]], 0), 1) -> Research
A106: 105597 | B106: 8/14/1956 | C106: Christfried | D106: Kabayashi | E106: M | F106: 5/11/1987 | G106: 2 | H106: A | I106: 0 | K106: 43841 | L106: d003 | M106: Senior Staff | N106: =INDEX(Table3[#All], MATCH(Table13[[#This Row],[Dept_Id]], Table3[[#All],[Dept_Id]], 0), 1) -> Human Resources
A107: 10065 | B107: 4/14/1963 | C107: Satosi | D107: Awdeh | E107: M | F107: 5/18/1988 | G107: 5 | H107: B | I107: 0 | K107: 40000 | L107: d005 | M107: Engineer | N107: =INDEX(Table3[#All], MATCH(Table13[[#This Row],[Dept_Id]], Table3[[#All],[Dept_Id]], 0), 1) -> Development
A108: 10066 | B108: 11/13/1952 | C108: Kwee | D108: Schusler | E108: M | F108: 2/26/1986 | G108: 1 | H108: PIP | I108: 0 | K108: 69736 | L108: d005 | M108: Senior Engineer | N108: =INDEX(Table3[#All], MATCH(Table13[[#This Row],[Dept_Id]], Table3[[#All],[Dept_Id]], 0), 1) -> Development
A109: 244689 | B109: 4/13/1956 | C109: Urs | D109: Saoudi | E109: M | F109: 9/2/1991 | G109: 7 | H109: B | I109: 0 | K109: 40000 | L109: d001 | M109: Staff | N109: =INDEX(Table3[#All], MATCH(Table13[[#This Row],[Dept_Id]], Table3[[#All],[Dept_Id]], 0), 1) -> Marketing
A110: 244689 | B110: 4/13/1956 | C110: Urs | D110: Saoudi | E110: M | F110: 9/2/1991 | G110: 7 | H110: B | I110: 0 | K110: 40000 | L110: d003 | M110: Staff | N110: =INDEX(Table3[#All], MATCH(Table13[[#This Row],[Dept_Id]], Table3[[#All],[Dept_Id]], 0), 1) -> Human Resources
A111: 10067 | B111: 1/7/1953 | C111: Claudi | D111: Stavenow | E111: M | F111: 3/4/1987 | G111: 2 | H111: C | I111: 0 | K111: 44642 | L111: d006 | M111: Senior Engineer | N111: =INDEX(Table3[#All], MATCH(Table13[[#This Row],[Dept_Id]], Table3[[#All],[Dept_Id]], 0), 1) -> Quality Management
A112: 10068 | B112: 11/26/1962 | C112: Charlene | D112: Brattka | E112: M | F112: 8/7/1987 | G112: 6 | H112: A | I112: 0 | K112: 87964 | L112: d007 | M112: Staff | N112: =INDEX(Table3[#All], MATCH(Table13[[#This Row],[Dept_Id]], Table3[[#All],[Dept_Id]], 0), 1) -> Sales
A113: 48885 | B113: 8/28/1958 | C113: Phuoc | D113: Antonisse | E113: M | F113: 2/18/1993 | G113: 9 | H113: B | I113: 0 | K113: 55736 | L113: d005 | M113: Senior Engineer | N113: =INDEX(Table3[#All], MATCH(Table13[[#This Row],[Dept_Id]], Table3[[#All],[Dept_Id]], 0), 1) -> Development
A114: 10069 | B114: 9/6/1960 | C114: Margareta | D114: Bierman | E114: F | F114: 11/5/1989 | G114: 10 | H114: A | I114: 0 | K114: 67932 | L114: d004 | M114: Technique Leader | N114: =INDEX(Table3[#All], MATCH(Table13[[#This Row],[Dept_Id]], Table3[[#All],[Dept_Id]], 0), 1) -> Production
... A116: 10070 | B116: 8/20/1955 | C116: Reuven | D116: Garigliano | E116: M | F116: 10/14/1985 | G116: 7 | H116: A | I116: 0 | K116: 55999 | L116: d008 | M116: Technique Leader | N116: =INDEX(Table3[#All], MATCH(Table13[[#This Row],[Dept_Id]], Table3[[#All],[Dept_Id]], 0), 1) -> Research
A117: 244492 | B117: 5/22/1958 | C117: Shaunak | D117: Pettit | E117: M | F117: 7/19/1994 | G117: 3 | H117: C | I117: 1 | J117: 11/14/2000 | K117: 63685 | L117: d005 | M117: Senior Engineer | N117: =INDEX(Table3[#All], MATCH(Table13[[#This Row],[Dept_Id]], Table3[[#All],[Dept_Id]], 0), 1) -> Development
A118: 10071 | B118: 1/21/1958 | C118: Hisao | D118: Lipner | E118: M | F118: 10/1/1987 | G118: 4 | H118: B | I118: 0 | K118: 40000 | L118: d003 | M118: Staff | N118: =INDEX(Table3[#All], MATCH(Table13[[#This Row],[Dept_Id]], Table3[[#All],[Dept_Id]], 0), 1) -> Human Resources
A119: 215615 | B119: 2/13/1957 | C119: Bader | D119: Chinal | E119: F | F119: 1/8/1990 | G119: 10 | H119: C | I119: 0 | K119: 40000 | L119: d004 | M119: Engineer | N119: =INDEX(Table3[#All], MATCH(Table13[[#This Row],[Dept_Id]], Table3[[#All],[Dept_Id]], 0), 1) -> Production
A120: 215615 | B120: 2/13/1957 | C120: Bader | D120: Chinal | E120: F | F120: 1/8/1990 | G120: 10 | H120: C | I120: 0 | K120: 40000 | L120: d006 | M120: Engineer | N120: =INDEX(Table3[#All], MATCH(Table13[[#This Row],[Dept_Id]], Table3[[#All],[Dept_Id]], 0), 1) -> Quality Management
A121: 10072 | B121: 5/15/1952 | C121: Hironoby | D121: Sidou | E121: F | F121: 7/21/1988 | G121: 8 | H121: B | I121: 0 | K121: 40000 | L121: d005 | M121: Senior Engineer | N121: =INDEX(Table3[#All], MATCH(Table13[[#This Row],[Dept_Id]], Table3[[#All],[Dept_Id]], 0), 1) -> Development
A122: 10073 | B122: 2/23/1954 | C122: Shir | D122: McClurg | E122: M | F122: 12/1/1991 | G122: 5 | H122: C | I122: 0 | K122: 56473 | L122: d006 | M122: Engineer | N122: =INDEX(Table3[#All], MATCH(Table13[[#This Row],[Dept_Id]], Table3[[#All],[Dept_Id]], 0), 1) -> Quality Management
A123: 95280 | B123: 2/14/1960 | C123: Owen | D123: Hiraishi | E123: F | F123: 8/7/1985 | G123: 10 | H123: S | I123: 0 | K123: 40000 | L123: d004 | M123: Senior Engineer | N123: =INDEX(Table3[#All], MATCH(Table13[[#This Row],[Dept_Id]], Table3[[#All],[Dept_Id]], 0), 1) -> Production
A124: 10074 | B124: 8/28/1955 | C124: Mokhtar | D124: Bernatsky | E124: F | F124: 8/13/1990 | G124: 8 | H124: PIP | I124: 1 | J124: 5/22/1995 | K124: 61714 | L124: d005 | M124: Technique Leader | N124: =INDEX(Table3[#All], MATCH(Table13[[#This Row],[Dept_Id]], Table3[[#All],[Dept_Id]], 0), 1) -> Development
A125: 10075 | B125: 3/9/1960 | C125: Gao | D125: Dolinsky | E125: F | F125: 3/19/1987 | G125: 4 | H125: B | I125: 0 | K125: 43815 | L125: d005 | M125: Senior Engineer | N125: =INDEX(Table3[#All], MATCH(Table13[[#This Row],[Dept_Id]], Table3[[#All],[Dept_Id]], 0), 1) -> Development
A126: 37473 | B126: 3/6/1952 | C126: Prasadram | D126: Valette | E126: M | F126: 2/16/1994 | G126: 3 | H126: PIP | I126: 0 | K126: 55963 | L126: d002 | M126: Staff | N126: =INDEX(Table3[#All], MATCH(Table13[[#This Row],[Dept_Id]], Table3[[#All],[Dept_Id]], 0), 1) -> Finance
A127: 10076 | B127: 6/13/1952 | C127: Erez | D127: Ritzmann | E127: F | F127: 7/9/1985 | G127: 9 | H127: B | I127: 0 | K127: 47319 | L127: d005 | M127: Senior Engineer | N127: =INDEX(Table3[#All], MATCH(Table13[[#This Row],[Dept_Id]], Table3[[#All],[Dept_Id]], 0), 1) -> Development
...

Sheet Dept_Info
A1: Dep_Name | B1: Dept_Id
A2: Marketing | B2: d001
A3: Finance | B3: d002
A4: Human Resources | B4: d003
A5: Production | B5: d004
A6: Development | B6: d005
A7: Quality Management | B7: d006
A8: Sales | B8: d007
A9: Research | B9: d008
A10: Customer Service | B10: d009

Sheet Business Context
B1: Business Context
B2: A mid-sized organization wants to improve its human resource planning, retention strategy, and departmental efficiency. The company has been collecting employee data over the years,
B3: including demographics, work history, performance, and attrition details. Additionally, it maintains a department-level database with department names and IDs.
B5: With rising attrition in some departments and concerns around performance consistency, the HR and Leadership teams want a data-driven understanding of employee trends—both current
B6: and historical—to guide decisions on hiring, promotions, and organizational restructuring.
B8: Problem Statememt
B10: To analyze employee demographics, performance, attrition trends, and departmental structures to deliver insights that:
C11: Improve talent retention strategies
C12: Identify performance bottlenecks
C13: Support department-level workforce planning
C14: Forecast potential risks such as high attrition or skill gaps
B16: Data Description | Data Dictionary
C18: Employee_Info: | F18: Dept_Info:
C19: Columns | D19: Description | F19: Columns | G19: Description
C20: Emp_Id | D20: Employee_id | F20: Dept_id | G20: Department id
C21: DOB | D21: Date of Birth | F21: Dep_Name | G21: Name of the department
C22: first_name | D22: First name of employee
C23: last_name | D23: Last name of employee
C24: Gender | D24: Gender of employee, male or female
C25: DoJ | D25: Date of Joining/ Hiring
C26: no_of_projects | D26: Number of projects worked on
C27: Last_performance_rating | D27: Last year performance ratin--> A, B, C, PIP & S
C28: Left? | D28: Employee left the organization or not? i.e. 0 or 1
C29: last_date | D29: Last date of employement(Exit Date)
C30: Salary | D30: Salary of employee
C31: Dept_Id | D31: Id of Dept in which employee works
C32: Title | D32: Designation of Employee
C35: Ratings description:
C37: Rating | D37: Meaning | E37: Description
C38: A | D38: Excellent / Outstanding | E38: Top performer, exceeds expectations consistently. Often eligible for promotions, bonuses, leadership roles.
C39: B | D39: Good / Meets Expectations | E39: Solid performer. Delivers what’s expected; may occasionally go beyond. Reliable and consistent.
C40: C | D40: Needs Improvement / Below Expectations | E40: Underperforming slightly. May need coaching or upskilling. Not serious yet, but needs monitoring.
C41: PIP | D41: Performance Improvement Plan | E41: Officially under review due to poor performance. Risk of termination if performance doesn't improve.
C42: S | D42: Star Performer / Strategic Contributor | E42: Often used in some companies for elite talent. High-potential, future leader, or mission-critical employee.

Sheet Expected Deliverables
D2: This Mini Project Focuses on Data Transformations, building KPI using Statistical functions & Summarizations using Pivot Tables
B4: 1. Before proceeding with analysis, make sure Date Columns and Salary are in correct format.
B5: 2. In the "Employee_Info" sheet, add a new column that saves the "Dep_Name" for each Employee.
B6: 3. Generate the following KPIs:
C7: a. No. of Employees who left the firm
C8: b. No. of Employees in the Leadership Role
C9: c. Total Employees associated with the firm
B11: 4. Perform the following analysis
C12: a. Employee Retention & Attrition
C13: How many %employees have left the company?
C14: What is the average tenure of employees who left?
C16: b. Performance & Productivity
C17: Is there any correlation between number of projects and performance rating?
C18: Which departments have the highest number of top performers?
C20: c. Salary Analysis
C21: What is the average salary by department?
C22: Are male or female employees paid more on average?
C24: d. Hiring Trends
C25: How many employees joined each year?
C26: Which departments saw the most hiring in the past 2 years?
B28: 5. Are there any employees with poor performance and high salary?
D29: hint: use conditional formattings

Sheet Analysis| Summarization
B3: KPIs: | I3: sum() | J3: countifs()
C4: a. No. of Employees who left the firm | I4: =SUM(Table15[Left?]) -> 44 | J4: =COUNTIFS(Table15[Left?], 1) -> 44
C5: b. No. of Employees in the Leadership Role | I5: =COUNTIFS(Table15[Title], 'New_employee(Cleaned)'!$M$487) -> 29
C6: c. Total Employees associated with the firm | I6: =COUNTIFS(Table15[Left?], 0) -> 456 | J6: =I7-I4 -> 456 | K6: =COUNTBLANK(Table15[last_date]) -> 456
C7: d. Total volume of employees | I7: =COUNTA(Table1[Emp_Id]) -> 500
B10: a. Employee Retention & Attrition
C11: How many %employees have left the company? | I11: What is the average tenure of employees who left?
C13: Left the Org? | D13: Emp_Count | J13: Left? | K13: 1
C14: 0 | D14: 0.912
C15: 1 | D15: 0.088 | J15: Avg. Tenure
C16: Grand Total | D16: 1 | J16: 7.3863636
B19: b. Performance & Productivity
B20: Is there any correlation between number of projects and performance rating? | J20: Which departments have the highest number of top performers?
C22: Projects done | D22: Avg. Ratings | L22: Last_performance_rating | M22: (Multiple Items)
C23: 1 | D23: 3.0181818
C24: 2 | D24: 3.1111111 | L24: Departments | M24: Top Performers
C25: 3 | D25: 3.2631579 | L25: Production | M25: 50
C26: 4 | D26: 3.1428571 | L26: Development | M26: 41
C27: 5 | D27: 2.8363636 | L27: Sales | M27: 28
C28: 6 | D28: 3 | L28: Research | M28: 15
C29: 7 | D29: 3.037037 | L29: Customer Service | M29: 15
C30: 8 | D30: 2.9411765 | L30: Finance | M30: 12
C31: 9 | D31: 3.1764706 | L31: Marketing | M31: 10
C32: 10 | D32: 2.8627451 | L32: Human Resources | M32: 9
C33: Grand Total | D33: 3.03 | L33: Quality Management | M33: 8
L34: Grand Total | M34: 188
D35: =CORREL($C$23:$C$32, $D$23:$D$32) -> -0.36246429
D36: =CORREL($C$23:$C$32, $D$23:$D$32)
B38: c. Salary Analysis
B39: What is the average salary by department? | H39: Are male or female employees paid more on average?
C42: Departments | D42: Avg. Salary | I42: Grenders | J42: Avg. Salary
C43: Customer Service | D43: 48253.889 | I43: F | J43: 54052.299
C44: Development | D44: 48362.054 | I44: M | J44: 52607.634
C45: Finance | D45: 59878.667 | I45: Grand Total | J45: 53168.164
C46: Human Resources | D46: 48254.593
C47: Marketing | D47: 65131.667
C48: Production | D48: 48702.5
C49: Quality Management | D49: 49048.037
C50: Research | D50: 48469.927
C51: Sales | D51: 69925.347
C52: Grand Total | D52: 53168.164
B54: d. Hiring Trends
B55: How many employees joined each year? | G55: Which departments saw the most hiring in the past 2 years?
C57: Joining Years | D57: Emp_Count
C58: 1985 | D58: 51 | H58: DoJ (Year) | I58: (Multiple Items)
C59: 1986 | D59: 69
C60: 1987 | D60: 56 | H60: Departments | I60: Emp Joined
C61: 1988 | D61: 52 | H61: Customer Service | I61: 1
C62: 1989 | D62: 44 | H62: Development | I62: 3
C63: 1990 | D63: 50 | H63: Human Resources | I63: 1
C64: 1991 | D64: 41 | H64: Production | I64: 2
C65: 1992 | D65: 41 | H65: Quality Management | I65: 1
C66: 1993 | D66: 23 | H66: Research | I66: 3
C67: 1994 | D67: 24 | H67: Grand Total | I67: 11
C68: 1995 | D68: 22
C69: 1996 | D69: 10
C70: 1997 | D70: 6
C71: 1998 | D71: 6
C72: 1999 | D72: 5
C73: Grand Total | D73: 500
B76: 5. Are there any employees with poor performance and high salary?
C78: =SUM(Table15[Performance issues?]) -> 8

Sheet HR ANALYSIS
A1: HR DATA ANALYSIS
D4: ='Analysis| Summarization'!$I$4 -> 44 | G4: ='Analysis| Summarization'!$I$5 -> 29 | J4: ='Analysis| Summarization'!$I$6 -> 456 | M4: ='Analysis| Summarization'!$I$7 -> 500 | P4: =GETPIVOTDATA("[Measures].[Average of Duration]",'Analysis| Summarization'!$J$15) -> 7.3863636
